Workbook

Sheet Export Summary
B3: This document was exported from Numbers. Each table was converted to an Excel worksheet. All other objects on each Numbers sheet were placed on separate worksheets. Please be aware that formula calculations may differ in Excel.
B7: Numbers Sheet Name | C7: Numbers Table Name | D7: Excel Worksheet Name
B9: Y2027 NPI - Vendor [TEMPLATE]
C10: 2027 NPI Supportability Summary - APO | D10: Y2027 NPI - Vendor _TEMPLATE_ -
C11: Resource Availability for Y2027 NPI Support | D11: Y2027 NPI - Vendor _TEMPLATE_ 1
C12: Y2027 RFP Breakdown | D12: Y2027 NPI - Vendor _TEMPLATE_ 2
C13: “All Drawings from the Sheet” | D13: Y2027 NPI - Vendor _TEMPLATE_ 3
B14: Vendor Status
C15: Table 1 | D15: Vendor Status
B16: 2027 NPI Supportability Summary
C17: 2027 NPI Supportability Summary - APO | D17: 2027 NPI Supportability Summary
B18: TE 2027 New Development Station List
C19: Vendor Engagement Scope | D19: TE 2027 New Development Station
B20: AE/SAE/ME 2027 New Development Station List
C21: TE Vendor Engagement Scope | D21: AE_SAE_ME 2027 New Development
B22: AE DFM 2027 New Development Station List
C23: Table 1 | D23: AE DFM 2027 New Development Sta
B24: Y2027 NPI - PRM (Anna) - 4/23v
C25: Resource Availability for Y2027 NPI Support | D25: Y2027 NPI - PRM (Anna) - 4_23v
C26: Y2026 Loading Breakdown (Apr ~ Sep) | D26: Y2027 NPI - PRM (Anna) - 4_23v1
C27: 2027 Idle Resources Name List for ALS_P | D27: Y2027 NPI - PRM (Anna) - 4_23v2
B28: Y2027 NPI - Innorev (Fiona)
C29: Resource Availability for Y2027 NPI Support | D29: Y2027 NPI - Innorev (Fiona) - R
C30: Y2026 Loading Breakdown (Apr ~ Sep) | D30: Y2027 NPI - Innorev (Fiona) - Y
B31: Y2027 NPI - JLK (Sean)
C32: Resource Availability for Y2027 NPI Support | D32: Y2027 NPI - JLK (Sean) - Resour
C33: Y2026 Loading Breakdown (Apr ~ Sep) | D33: Y2027 NPI - JLK (Sean) - Y2026
B34: Y2027 NPI - JLK IN 5/18v
C35: Resource Availability for Y2027 NPI Support | D35: Y2027 NPI - JLK IN 5_18v - Reso
C36: Y2027 RFP Breakdown | D36: Y2027 NPI - JLK IN 5_18v - Y202
B37: Y2027 NPI - VVDN IN 5/18
C38: Resource Availability for Y2027 NPI Support | D38: Y2027 NPI - VVDN IN 5_18 - Reso
C39: Y2027 RFP Breakdown | D39: Y2027 NPI - VVDN IN 5_18 - Y202
B40: Y2027 NPI - Cencorp (Rick)
C41: Resource Availability for Y2027 NPI Support | D41: Y2027 NPI - Cencorp (Rick) - Re
C42: Y2027 RFP Breakdown | D42: Y2027 NPI - Cencorp (Rick) - Y2
C43: Y2026 MP Loading Breakdown (Apr ~ Sep) | D43: Y2027 NPI - Cencorp (Rick) - Y1
C44: Y2026 MP Matrix | D44: Y2027 NPI - Cencorp (Rick) - Y3
B45: Y2027 NPI - HVS (Gene)
C46: Resource Availability for Y2027 NPI Support | D46: Y2027 NPI - HVS (Gene) - Resour
C47: Y2026 Loading Breakdown (Apr ~ Sep) | D47: Y2027 NPI - HVS (Gene) - Y2026
C48: Y2027 RFP Breakdown | D48: Y2027 NPI - HVS (Gene) - Y2027
C49: “All Drawings from the Sheet” | D49: Y2027 NPI - HVS (Gene) - Drawin
B50: Y2027 NPI - Pantamaster (JS)
C51: Resource Availability for Y2027 NPI Support | D51: Y2027 NPI - Pantamaster (JS) -
C52: Y2026 Loading Breakdown (Apr ~ Sep) | D52: Y2027 NPI - Pantamaster (JS) -1
B53: Y2027 NPI - CYG (Rick)
C54: Resource Availability for Y2027 NPI Support | D54: Y2027 NPI - CYG (Rick) - Resour
C55: Y2027 RFP Breakdown | D55: Y2027 NPI - CYG (Rick) - Y2027
C56: Y2026 MP Loading Breakdown (Apr ~ Sep) | D56: Y2027 NPI - CYG (Rick) - Y2026
B57: Y2027 NPI - Nextas (Jessie)
C58: Resource Availability for Y2027 NPI Support | D58: Y2027 NPI - Nextas (Jessie) - R
C59: Y2026 Loading Breakdown (Apr ~ Sep) | D59: Y2027 NPI - Nextas (Jessie) - Y
B60: Summary_Draft
C61: 2027 NPI Supportability Summary - APO | D61: Summary_Draft - 2027 NPI Suppor
B62: Y2027 NPI - PRM (Anna) - 4/13v
C63: Resource Availability for Y2027 NPI Support | D63: Y2027 NPI - PRM (Anna) - 4_13v
C64: Y2026 Loading Breakdown (Apr ~ Sep) | D64: Y2027 NPI - PRM (Anna) - 4_13v1
B65: Y2027 NPI - Accurate (Pratiksha) - 5/18
C66: Resource Availability for Y2027 NPI Support | D66: Y2027 NPI - Accurate (Pratiksha
B67: Y2027 NPI - SFO (Ankan) - 5/18
C68: Resource Availability for Y2027 NPI Support | D68: Y2027 NPI - SFO (Ankan) - 5_18
B69: [old] 2027 NPI Supportability Summary - APO
C70: 2027 NPI Supportability Summary - APO | D70: _old_ 2027 NPI Supportability S
B71: Sheet 1
C72: Commercial Levers | D72: Sheet 1 - Commercial Levers

Sheet Y2027 NPI - Vendor _TEMPLATE_ -
A1: GSSM DRI to complete based on assessment below
A2: 2027 RFP Stations (CPT GSSM RFPed Stations) | B2: GSSM Recommendation “Vendor ok2support ## RFP based on loading assessment” | C2: Loading | D2: Y2026 Ramp Resource Loading & Issue Feedback To be completed by GSM team, bucket feedback into key areas to streamline feedback. (Buckets: resources, delivery, bring up ?) (Apr’26 ~ Sep’26)
B3: “Vendor ok2support ## RFP based on loading assessment, but requires technical team evaluation of resource demand and quality” | C3: #%

Sheet Y2027 NPI - Vendor _TEMPLATE_ 1
A1: Resource Availability for Y2027 NPI Support
A2: Collect data from the vendor and populate here
A3: SI Name | B3: Resource | C3: Y2026 Loading | D3: Total Resource | E3: Resource Occupied for Y2026 Ramp | F3: Resource Leftover for Y2027 Brand-New Station NPI Build | G3: # of Stations Type can support | H3: Space Supportability (Y/N) | I3: Machining Capacity Supportability (Y/N) | J3: Assembly Capacity Supportability (Y/N) | K3: Quality Capacity Supportability (Y/N)
B4: PM | C4: {=SUM(E4:E11/SUM(D4:D11))} | G4: ## and validated with resource plan in matrix below | H4: Y, ## idle capacity | I4: Y, ## idle capacity | J4: Y, ## idle capacity | K4: Y, ## idle capacity
B5: ME
B6: EE
B7: SW
B8: FAE
B9: Assembly
B10: Debug
B11: Quality
B12: Total | D12: {=SUM(D4:D11)} -> 0 | E12: {=SUM(E4:E11)} -> 0 | F12: {=SUM(F4:F11)} -> 0

Sheet Y2027 NPI - Vendor _TEMPLATE_ 2
A1: Y2027 RFP Breakdown
A2: Collect data from the vendor and populate here
A3: SI Name | B3: Items
B4: Program
B5: Station Name
B6: Engagement Status (existing, new)
B7: PM
B8: ME
B9: EE
B10: SW
B11: FAE
B12: Quality
B13: Assembly
B14: Debug
B15: Quality

Sheet Y2027 NPI - Vendor _TEMPLATE_ 3

Sheet Vendor Status
A1: Table 1
B2: Fall 2027 Program Updated (Y/N, date) | C2: GSSM DRI
A3: Innorev
A4: PRM | B4: Y | C4: Anna Zhou
A5: JLK CN
A6: Cencorp | B6: Y | C6: Rick Deng
A7: JLK IN | B7: Y | C7: Urvil
A8: VVDN
A9: Accurate
A10: SFO
A11: Pentamaster
A12: CYG | B12: Y | C12: Rick Deng
A13: Next’s

Sheet 2027 NPI Supportability Summary
B2: 2027 SPOR - APO GSSM Recommendation | E2: NPI Resource | H2: MP Capacity
B3: SI Name (APO GSM) | C3: 2027 RFP Stations (CPT GSSM RFPed Stations) | D3: GSSM Recommendation “Vendor ok2support ## RFP based on loading assessment” | E3: Loading | F3: Y2026 Ramp Resource Loading & Issue Feedback To be completed by GSM team, bucket feedback into key areas to streamline feedback. (Buckets: resources, delivery, bring up ?) (Apr’26 ~ Sep’26) | G3: Y2027 NPI Build Resource Supportability Assessment To be completed by technical team moving forward (Apr’26 ~ Sep’26) | H3: Space Supportability | I3: Machining Capacity Supportability | J3: Assembly Capacity Supportability | K3: Quality Capacity Supportability
B4: PRM (Anna) | C4: iPhone V7x Station SA Barbie ALS-P Watch FACT Cyan | D4: High risk to awarding any new business at 2027 given the resource constraint and unvalidated expertise, pending PRM feedback on overall resource assessment strategy | E4: 0.81 | F4: Constraint Resource: PM/Technical/OSS shortage escalation Lack of operation management system: escalation from SQE/CapEx PM/Tech Ops on quality / delivery / on-site activities Lack of dedicated PM head to handle internal / external activities, led to Apple x-team spending huge efforts to bring up PRM cross areas | G4: Reported idle resource qty ONLY ok2support iPhone V7x ALSP Resource expertise NOT validated if able to meet new business requirement as all of them current scope at PRM are Non-A biz Help Needed: HWTE validate resource expertise upon request | H4: ◉ Available | I4: ◉ Available | J4: ◉ Available | K4: ◉ Available
B5: Cencorp (Rick) | C5: iPhone V7x Station SA Barbie ALS-P Odim Watch N25x FACT Cyan iPad J807/J830 DVI Portable K12P/K104 SeaSalt Volga | D5: OK2Support CPT RFP’ed stations but require close monitoring on ramp execution overlap and resource list sign off. | E5: 0.67 | F5: - No major highlight so far from X-team on Cencorp for Y26 Ramp - GSSM had deep dive review with Cencorp on resources including engineering, PM, FAE, production, OSS, and with name list supporting. Identified as medium-low risk. | G5: - Cencorp has rich experiences on conveyor station from both iPhone (Jasmine, Clematis, BEXT) and Portable (SeaSalt / Chocolate / Caramel) - Resource qty sufficient — after allocated to Y26 Ramp & Y27 NPI, there are still 11% resources leftover, however they are heavily engaged on ramps across CN/VN for multiple non-phone programs - Resource working experience: ~30% with +3 years experience with Cencorp | H5: ◉ Available | I5: ◉ Available | J5: ◉ Available | K5: ◉ Available
B6: Innorev (Fiona) | C6: iPhone V7x Station ALS-P Conveyor, Odin Conveyor, DCR/OS Tests, IQC AA stations. iPad J8x7 Station DVI Conveyor Watch N25x Station FACT21&Vent2 Conveyor, Conveyor Cyan Rotary Audio B798 station All in One Case, Open Short, IMU Camera. | D6: OK2Support CPT RFP’ed stations except Odin Conveyer (brand new to Innorev) | E6: 0.51 | F6: No major resource qtys issue for operation team but encountered DRI capability issue: An experienced operation mgr is expected on board asap; Sense & accuracy of communications is weak; OSS management team’s capability is below expectation. Engineer & operation team needs be more collaborated to ensure smooth transition from NPI to ramp; Quality team’s capability issue is a big issue which are continuously hi-lighted by SQE. | G6: Quality team qtys are sufficient but the capability of DRIs need to continuously improve. | H6: ◉ Available | I6: ◉ Available | J6: ◉ Available | K6: ◉ Available
B7: HVS (Gene) | C7: iPhone V7x Station ALS-P Conveyor, Odin Conveyor, DCR/OS Tests, IQC AA stations. Watch N25x Station FACT21&Vent2 Conveyor, Conveyor Cyan Rotary Audio B798 station All in One Case, Open Short, IMU Camera. | D7: OK2Support ONLY below stations [1] Audio - 3 stations [2] Phone V7x - ALSP [3] Phone V7x - Odin Same message from SI also shared with CPT team | E7: 0.64 | F7: X-team overall feedback from FXGL show HVS need to improve overall communication, PM capability, language barriers and OSS capability Very tough to own communication with Primary vendor to follow on-going design change / documents and parts purchasing - directly impacting EQ readiness HVS China plant capability should be improved further to support China local demand especially quality and purchases 2026 TE 4 stations will be under offline test and validation run in parallel and with on-going feedback/design change current resources are expected to stay longer than expected for now | G7: R&D / PM resource is OK2support limited stations and also need to focus on improving capability in China plan PM need to increase resource with language capability and also need to hired from local to decrease the reliance from Korea HQ TE resource also need to be allocated to support other programs CPT started engaging for India TE No enough resource to work to bridge/sync to primary SI for on-going works Similar feedback was also shared by SI directly to CPT team Support for 3rd station (Odin) is with plan to hire more resources | H7: ◉ Available | I7: ◉ Available | J7: ◉ Available | K7: ◉ Available
B8: JLK (Sean) | C8: iPhone V7x Station SA Barbie ALS-P Conveyor Odin Conveyor iPad J8x7 station DVI Conveyor Audio B798 Station Touch Conveyor Force Conveyor FACT Conveyor | D8: OK2Support | E8: 0.59 | F8: - No significant concerns have been identified regarding technical or operational resource quantities. However, quality-related issues remain, specifically: - Communication and data reporting competencies require further development. - Operations management headcount is sufficient, but the team lacks qualified project managers | G8: Since no entirely new station has been deployed for JLK, the technical design has no major change from the previous project. Consequently, JLK is able to provide stable support to those stations. | H8: ◉ Available | I8: ◉ Available | J8: ◉ Available | K8: ◉ Available
B9: Pantamaster (JS) | C9: iPhone V7x Station SA Barbie | D9: OK2Support | E9: {='Y2027 NPI - Pantamaster (JS) - '!C3} -> 0.5390625 | F9: - No resource issue to support TE. - Current TE resources have Apple project experience exposure. | H9: ◉ Available | I9: ◉ Available | J9: ◉ Available | K9: ◉ Available
B10: CYG (Rick) | C10: iPhone V7x Station IQC AA Test DCR/OR Test | D10: OK2Support | E10: 0.48 | F10: - CYG FY26 demand 19% decreased compared to FY25 - CYG key talents remain high retention - No major highlight so far from X-team on CYG for Y26 ramp | G10: - Standalone & less complex station - Only two new stations RFP engaged - Resource qty sufficient | H10: ◉ Available | I10: ◉ Available | J10: ◉ Available | K10: ◉ Available
B11: Nextas (Jessie) | C11: iPhone V7x Station IQC AA stations DCR/OS Tests | D11: OK2Support | E11: 0.16 | F11: -No resource issue as same group with Bojay which’s strong Engineer support NPI if need -Share same VN facility with Bojay, Lasteck will be ready to use by May/E | H11: ◉ Available | I11: ◉ Available | J11: ◉ Available | K11: ◉ Available
B12: JLK IN | C12: US GSSM team to fill out (need to confirm data above captures india or not) | D12: OK2Support | E12: 0.71 | F12: New Plant 3 up and running in Hosur, have space for expansion if need be Issues seen for competent PM & SCM teams | G12: Significant increase new high complexity stations in audio + phone (conveyors) Engg support from JLK China is critical for success PM + SCM hiring to be monitored. | H12: ◉ Available | I12: ◉ Available | J12: ◉ Available | K12: ◉ Available
B13: Accurate | C13: US GSSM team to fill out | D13: Ok2Support (same scope as 2026) | E13: 0.6 | F13: - Engg Resource constrained from a capability standpoint | G13: - Engg team remains a bottleneck, capacity to be proven through V6Y EVT, CP : | H13: ◉ Available | I13: ◉ Available | J13: ◉ Available | K13: ◉ Available
B14: VVDN | C14: US GSSM team to fill out | D14: OK2Support | E14: 0.74 | F14: Steep ramp up for DVI + Magnolia MLB RE is demanding maximum resource compared to TE | G14: InHouse Machining capacity needs to be increased PM + Engg resource needs to be strengthened | H14: ◉ Available | I14: ◉ Available | J14: ◉ Available | K14: ◉ Available
B15: SFO | C15: US GSSM team to fill out | D15: High Risk for NB- Scope to be limited only to retrofits | E15: 0.39 | F15: -Major operation scale up issues in 2026 Poor supplier management Multiple Quality failures observed | G15: No committed action from SFO leadership Restrict scope to only N-1 retrofits | H15: ◉ Available | I15: ◉ Available | J15: ◉ Available | K15: ◉ Available

Sheet TE 2027 New Development Station
A1: Vendor Engagement Scope
B2: CapEx Space | C2: LOB | D2: Program | E2: Station | F2: Launch Timing | G2: Line Count | H2: Vendor | I2: CN/Global | J2: NPI Location | K2: MP Geo Impacted | L2: SPOR Lock Date | M2: Intercept EIH | N2: Trending GSSM Recommendation | O2: Station Resource/Capacity Supportability (APO Fill - Y/N) | P2: Comments
A3: V7x
A4: ALS-P Conveyor
B5: TE | C5: Phone | D5: V7x | E5: ALS-P Conveyor | F5: Fall’27 | H5: Innorev | I5: China | J5: China | K5: China/India | L5: 46127 | M5: P1 EIH Jun/M | O5: Y - Resource/ capability OK2Ssupport. | P5: 1NB in P1, 1 in P2, 1 in EVT for conveyor; 3x each for standalone
B6: TE | C6: Phone | D6: V7x | E6: ALS-P Conveyor | F6: Fall’27 | H6: JLK | I6: Global | J6: China | K6: China/India | L6: 46127 | M6: P1 EIH Jun/M | O6: Y - Resource/ capability OK2Ssupport.
B7: TE | C7: Phone | D7: V7x | E7: ALS-P Conveyor | F7: Fall’27 | H7: Cencorp | I7: China | J7: China | K7: China/India | L7: 46127 | M7: P1 EIH Jun/M | O7: Y - Resource/ capability OK2Ssupport. | P7: updated based on Cencorp latest shared resource plan on 4/17
B8: TE | C8: Phone | D8: V7x | E8: ALS-P Conveyor | F8: Fall’27 | H8: HVS | I8: Global | J8: China | K8: China/India | L8: 46127 | M8: P1 EIH Jun/M | O8: Y - Leveraging 26 experience in ALSP but considering free-PRC and no BOM, can’t catch P1 timeline
B9: TE | C9: Phone | D9: V7x | E9: ALS-P Conveyor | F9: Fall’27 | H9: PRM | I9: China | J9: China | K9: China/India | L9: 46127 | M9: P1 EIH Jun/M | O9: N (insufficient & in-capable resource highlight by x-team during Y2026 iPhone Ramp)
B10: TE | C10: Phone | D10: V7x | E10: ALS-P Conveyor | F10: Fall’27 | H10: VVDN | I10: Global | J10: China | K10: China/India | L10: 46127 | M10: P1 EIH Jun/M | P10: IPO to input
A11: Odin conveyor
B12: TE | C12: Phone | D12: V7x | E12: Odin conveyor | F12: Fall’27 | H12: Innorev | I12: China | J12: China | K12: China/India | L12: 46127 | M12: P1 EIH Jun/M | O12: N - SQE limitation | P12: Out for RFP
B13: TE | C13: Phone | D13: V7x | E13: Odin conveyor | F13: Fall’27 | H13: JLK | I13: Global | J13: China | K13: China/India | L13: 46127 | M13: P1 EIH Jun/M | O13: Y - Resource/ capability OK2Ssupport.
B14: TE | C14: Phone | D14: V7x | E14: Odin conveyor | F14: Fall’27 | H14: Cencorp | I14: China | J14: China | K14: China/India | L14: 46127 | M14: P1 EIH Jun/M | O14: Y - per Hemik this station is likely to be integrated into Clematis, but regardless it will be incremental design work for Cencorp
B15: TE | C15: Phone | D15: V7x | E15: Odin conveyor | F15: Fall’27 | H15: HVS | I15: Global | J15: China | K15: China/India | L15: 46127 | M15: P1 EIH Jun/M | O15: Y - OK2Support with additional resource hiring plan / Space is ok2support | P15: RFQ submitted
B16: TE | C16: Phone | D16: V7x | E16: Odin conveyor | F16: Fall’27 | H16: VVDN | I16: Global | J16: China | K16: China/India | L16: 46127 | M16: P1 EIH Jun/M | P16: IPO to input
A17: IQC AA stations
B18: TE | C18: Phone | D18: V7x | E18: IQC AA stations | F18: Fall’27 | H18: Innorev | I18: China | J18: China | K18: China/India | L18: 46127 | M18: P1 EIH Jun/M | O18: Y - Resource/ capability OK2Ssupport.
B19: TE | C19: Phone | D19: V7x | E19: IQC AA stations | F19: Fall’27 | H19: HVS | I19: Global | J19: China | K19: China/India | L19: 46127 | M19: P1 EIH Jun/M | O19: N - PM and other resource limitation considering new design & Free-PRC / China settlement in 2026
B20: TE | C20: Phone | D20: V7x | E20: IQC AA stations | F20: Fall’27 | H20: VVDN | I20: Global | J20: China | K20: China/India | L20: 46127 | M20: P1 EIH Jun/M | P20: IPO to input
B21: TE | C21: Phone | D21: V7x | E21: IQC AA stations | F21: Fall’27 | H21: CYG (already engaged) | I21: Global | J21: China | K21: China/India | L21: 46127 | M21: P1 EIH Jun/M | O21: Y
B22: TE | C22: Phone | D22: V7x | E22: IQC AA stations | F22: Fall’27 | H22: Nextas | I22: China | J22: China | K22: China/India | L22: 46127 | M22: P1 EIH Jun/M | O22: Y
A23: DCR/OS Tests
B24: TE | C24: Phone | D24: V7x | E24: DCR/OS Tests | F24: Fall’27 | H24: Innorev | I24: China | J24: China | K24: China/India | L24: 46127 | M24: P1 EIH Jun/M | O24: Y - Resource/ capability OK2Ssupport.
B25: TE | C25: Phone | D25: V7x | E25: DCR/OS Tests | F25: Fall’27 | H25: HVS | I25: Global | J25: China | K25: China/India | L25: 46127 | M25: P1 EIH Jun/M | O25: N - PM and other resource limitation considering new design & Free-PRC / China settlement in 2026
B26: TE | C26: Phone | D26: V7x | E26: DCR/OS Tests | F26: Fall’27 | H26: VVDN | I26: Global | J26: China | K26: China/India | L26: 46127 | M26: P1 EIH Jun/M | P26: IPO to input
B27: TE | C27: Phone | D27: V7x | E27: DCR/OS Tests | F27: Fall’27 | H27: CYG (already engaged) | I27: Global | J27: China | K27: China/India | L27: 46127 | M27: P1 EIH Jun/M | O27: Y
B28: TE | C28: Phone | D28: V7x | E28: DCR/OS Tests | F28: Fall’27 | H28: Nextas | I28: China | J28: China | K28: China/India | L28: 46127 | M28: P1 EIH Jun/M | O28: Y
A29: SA-Barbie
B30: TE | C30: Phone | D30: V7x | E30: SA-Barbie | F30: Fall’27 | H30: JLK | I30: Global | J30: China | K30: China/India | L30: 46127 | M30: P1 EIH Jun/M | N30: JLK or Cencorp | O30: Y - Resource/ capability OK2Ssupport.
B31: TE | C31: Phone | D31: V7x | E31: SA-Barbie | F31: Fall’27 | H31: Cencorp | I31: China | J31: China | K31: China/India | L31: 46127 | M31: P1 EIH Jun/M | O31: Y - Resource/ capability OK2Ssupport.
B32: TE | C32: Phone | D32: V7x | E32: SA-Barbie | F32: Fall’27 | H32: PRM | I32: China | J32: China | K32: China/India | L32: 46127 | M32: P1 EIH Jun/M | O32: N (insufficient & in-capable resource highlight by x-team during Y2026 iPhone Ramp)
B33: TE | C33: Phone | D33: V7x | E33: SA-Barbie | F33: Fall’27 | H33: Pentamaster | I33: Global | J33: China | K33: China/India | L33: 46127 | M33: P1 EIH Jun/M | O33: Y - Resource/ capability OK2Ssupport.
A34: J8x7
A35: DVI Conveyor RFP
B36: TE | C36: iPad | D36: J8x7 | E36: DVI Conveyor RFP | H36: Innorev | I36: China | J36: China | K36: China/Vietnam | L36: 46141 | M36: P2 EIH Jun/E | O36: Y - Resource/ capability OK2Ssupport.
B37: TE | C37: iPad | D37: J8x7 | E37: DVI Conveyor RFP | H37: JLK | I37: Global | J37: China | K37: China/Vietnam | L37: 46141 | M37: P2 EIH Jun/E | O37: Y - Resource/ capability OK2Ssupport.
B38: TE | C38: iPad | D38: J8x7 | E38: DVI Conveyor RFP | H38: Cencorp | I38: China | J38: China | K38: China/Vietnam | L38: 46141 | M38: P2 EIH Jun/E | O38: Y - Resource/ capability OK2Ssupport. | P38: updated based on Cencorp latest shared resource plan on 4/17
A39: B798
A40: ALL in One Case
B41: TE | C41: Audio | D41: B798 | E41: ALL in One Case | F41: Fall’27 | H41: Innorev | I41: China | J41: China | K41: China | L41: Open | M41: P2 EIH Jun/E | O41: Y - Resource/ capability OK2Ssupport. | P41: Out for RFP
B42: TE | C42: Audio | D42: B798 | E42: ALL in One Case | F42: Fall’27 | H42: JLK | I42: Global | J42: China | K42: China | L42: Open | M42: P2 EIH Jun/E | O42: No RFP received | P42: Out for RFP
B43: TE | C43: Audio | D43: B798 | E43: ALL in One Case | F43: Fall’27 | H43: PRM | I43: China | J43: China | K43: China | L43: Open | M43: P2 EIH Jun/E | O43: Not received RFP | P43: Out for RFP
B44: TE | C44: Audio | D44: B798 | E44: ALL in One Case | F44: Fall’27 | H44: Pentamaster | I44: Global | J44: China | K44: China | L44: Open | M44: P2 EIH Jun/E | O44: No RFP received | P44: Out for RFP
B45: TE | C45: Audio | D45: B798 | E45: ALL in One Case | F45: Fall’27 | H45: HVS | I45: Global | J45: China | K45: China | L45: Open | M45: P2 EIH Jun/E | O45: Y - already aligned with CPT and list submitted / Capacity & Resource ok to support (Produced in Korea for NPI build) - need to check station name | P45: Out for RFP
A46: Open Short
B47: TE | C47: Audio | D47: B798 | E47: Open Short | F47: Fall’27 | H47: Innorev | I47: China | J47: China | K47: China | L47: Open | M47: P2 EIH Jun/E | O47: Y - Resource/ capability OK2Ssupport. | P47: Out for RFP
B48: TE | C48: Audio | D48: B798 | E48: Open Short | F48: Fall’27 | H48: JLK | I48: Global | J48: China | K48: China | L48: Open | M48: P2 EIH Jun/E | O48: No RFP received | P48: Out for RFP
B49: TE | C49: Audio | D49: B798 | E49: Open Short | F49: Fall’27 | H49: PRM | I49: China | J49: China | K49: China | L49: Open | M49: P2 EIH Jun/E | O49: Not received RFP | P49: Out for RFP
B50: TE | C50: Audio | D50: B798 | E50: Open Short | F50: Fall’27 | H50: Pentamaster | I50: Global | J50: China | K50: China | L50: Open | M50: P2 EIH Jun/E | O50: No RFP received | P50: Out for RFP
B51: TE | C51: Audio | D51: B798 | E51: Open Short | F51: Fall’27 | H51: HVS | I51: Global | J51: China | K51: China | L51: Open | M51: P2 EIH Jun/E | O51: Y - already aligned with CPT and list submitted / Capacity & Resource ok to support (Produced in Korea for NPI build) - need to check station name | P51: Out for RFP
A52: IMU Camera
B53: TE | C53: Audio | D53: B798 | E53: IMU Camera | F53: Fall’27 | H53: Innorev | I53: China | J53: China | K53: China | L53: Open | M53: P2 EIH Jun/E | O53: Y - Resource/ capability OK2Ssupport. | P53: Out for RFP
B54: TE | C54: Audio | D54: B798 | E54: IMU Camera | F54: Fall’27 | H54: JLK | I54: Global | J54: China | K54: China | L54: Open | M54: P2 EIH Jun/E | O54: No RFP received | P54: Out for RFP
B55: TE | C55: Audio | D55: B798 | E55: IMU Camera | F55: Fall’27 | H55: PRM | I55: China | J55: China | K55: China | L55: Open | M55: P2 EIH Jun/E | O55: Not received RFP | P55: Out for RFP
B56: TE | C56: Audio | D56: B798 | E56: IMU Camera | F56: Fall’27 | H56: Pentamaster | I56: Global | J56: China | K56: China | L56: Open | M56: P2 EIH Jun/E | O56: No RFP received | P56: Out for RFP
B57: TE | C57: Audio | D57: B798 | E57: IMU Camera | F57: Fall’27 | H57: HVS | I57: Global | J57: China | K57: China | L57: Open | M57: P2 EIH Jun/E | O57: Y - already aligned with CPT and list submitted / Capacity & Resource ok to support (Produced in Korea for NPI build) - need to check station name | P57: Out for RFP
A58: Audio Conveyor
B59: TE | C59: Audio | D59: B798 | E59: Audio Conveyor | F59: Fall’27 | H59: JLK | I59: Global | J59: China | K59: China | L59: Done | M59: P2 EIH Jun/E | O59: Y - Resource/ capability OK2Ssupport.
B60: TE | C60: Audio | D60: B798 | E60: Audio Conveyor | F60: Fall’27 | H60: HVS | I60: Global | J60: China | K60: China | L60: Done | M60: P2 EIH Jun/E | O60: Y - already aligned with CPT and list submitted / Capacity & Resource ok to support (Produced in Korea for NPI build) - need to check station name | P60: Out for RFP
A61: N25x
A62: Conveyor Fact/Vent
B63: TE | C63: Watch | D63: N25x | E63: Conveyor Fact/Vent | F63: Fall’27 | H63: Innorev | I63: China | J63: China | K63: China/Vietnam | L63: 46141 | M63: P2 EIH Jun/E | O63: Y - Resource/ capability OK2Ssupport. | P63: Invited JLK Innorev Cencorp PRM Hyvision Pentamaster
B64: TE | C64: Watch | D64: N25x | E64: Conveyor Fact/Vent | F64: Fall’27 | H64: JLK | I64: Global | J64: China | O64: No, commercial reason as no profit
B65: TE | C65: Watch | D65: N25x | E65: Conveyor Fact/Vent | F65: Fall’27 | H65: PRM | I65: China | J65: China | O65: N (insufficient & in-capable resource highlight by x-team during Y2026 iPhone Ramp)
B66: TE | C66: Watch | D66: N25x | E66: Conveyor Fact/Vent | F66: Fall’27 | H66: Pentamaster | I66: Global | J66: China | O66: No RFP received
B67: TE | C67: Watch | D67: N25x | E67: Conveyor Fact/Vent | F67: Fall’27 | H67: HVS | I67: Global | J67: China | O67: N - Aligned not to proceed (with Tyler)
A68: Conveyor Cyan Rotary
B69: TE | C69: Watch | D69: N25x | E69: Conveyor Cyan Rotary | F69: Fall’27 | H69: Innorev | I69: China | J69: China | K69: China/Vietnam | L69: Open | M69: P1 Sept | O69: Y - Resource/ capability OK2Ssupport. | P69: Out for RFP
B70: TE | C70: Watch | D70: N25x | E70: Conveyor Cyan Rotary | F70: Fall’27 | H70: JLK | I70: Global | J70: China | K70: China/Vietnam | L70: Open | M70: P1 Sept | O70: No, commercial reason as no profit | P70: Out for RFP
B71: TE | C71: Watch | D71: N25x | E71: Conveyor Cyan Rotary | F71: Fall’27 | H71: PRM | I71: China | J71: China | K71: China/Vietnam | L71: Open | M71: P1 Sept | O71: N (insufficient & in-capable resource highlight by x-team during Y2026 iPhone Ramp) | P71: Out for RFP
B72: TE | C72: Watch | D72: N25x | E72: Conveyor Cyan Rotary | F72: Fall’27 | H72: Pentamaster | I72: Global | J72: China | K72: China/Vietnam | L72: Open | M72: P1 Sept | O72: No RFP received | P72: Out for RFP
B73: TE | C73: Watch | D73: N25x | E73: Conveyor Cyan Rotary | F73: Fall’27 | H73: HVS | I73: Global | J73: China | K73: China/Vietnam | L73: Open | M73: P1 Sept | O73: N - Aligned not to proceed (with Tyler) | P73: Out for RFP
A74: K12p
A75: Seasalt Conveyor
B76: TE | C76: Portables | D76: K12p | E76: Seasalt Conveyor | H76: Cencorp | I76: China | J76: China | O76: Y - Cencorp already planned the required resource early

Sheet AE_SAE_ME 2027 New Development 
A1: TE Vendor Engagement Scope
A2: CapEx Space | B2: LOB | C2: Program | D2: Station | E2: Launch Timing | F2: Line Count | G2: Vendor | H2: CN/Global | I2: NPI Location | J2: MP Geo Impacted | K2: SPOR Lock Date | L2: Intercept EIH | M2: Trending GSSM Recommendation | N2: Station Resource/Capacity Supportability (APO Fill - Y/N) | O2: Comments
A3: AE | B3: Phone | C3: V7x | D3: ALS-P Conveyor (example) | E3: Fall’27 | G3: Innorev | H3: China | I3: China | J3: China/India | K3: 46127 | L3: P1 EIH Jun/M | N3: Y - Resource/ capability OK2Ssupport. | O3: 1NB in P1, 1 in P2, 1 in EVT for conveyor; 3x each for standalone
A4: AE | B4: iPad | C4: J8x7 | D4: CG Mic & ALS PnP | E4: Spring’27 | G4: ASM | H4: Global | I4: China | J4: VN | L4: P2 Jul
A5: AE | B5: iPad | C5: J8x7 | D5: PB Housing Measurement | E5: Spring’27 | G5: ASM | H5: Global | I5: China | J5: VN | L5: P2 Jul
A6: AE | B6: iPad | C6: J8x7 | D6: BIM (PB Install) | E6: Spring’27 | G6: ASM | H6: Global | I6: China | J6: VN | L6: P2 Jul
A7: AE | B7: iPhone | C7: V7x | D7: AHDP | E7: Fall’27 | G7: BZ | H7: China | I7: China | J7: China/India | K7: CQ’4 2026
A8: AE | B8: iPhone | C8: V7x | D8: BHDP | E8: Fall’27 | G8: BZ | H8: China | I8: China | J8: China/India | K8: CQ’4 2026
A9: AE | B9: iPhone | C9: V7x | D9: FIFO | E9: Fall’27 | G9: JST | H9: China | I9: China | J9: China | K9: CQ’4 2026
A10: AE | B10: iPhone | C10: V7x | D10: BGS1 | E10: Fall’27 | G10: Secote | H10: China | I10: China | J10: China | K10: CQ’4 2026
A11: AE | B11: iPhone | C11: V7x | D11: BGS2 | E11: Fall’27 | G11: Secote | H11: China | I11: China | J11: China | K11: CQ’4 2026
A12: AE | B12: iPhone | C12: V7x | D12: CIM | E12: Fall’27 | G12: JST | H12: China | I12: China | J12: China | K12: CQ’4 2026
A13: AE | B13: iPhone | C13: V7x | D13: Laser All-in-one (TBD) | E13: Fall’27 | G13: Hans-Lemax | H13: China/Global | I13: China | J13: China/Global | K13: CQ’4 2026
A14: AE | B14: iPhone | C14: V7x | D14: AHDP | E14: Fall’27 | G14: Taowine | H14: China | I14: China | J14: China | K14: CQ’4 2026
A15: AE | B15: iPhone | C15: V7x | D15: BHDP | E15: Fall’27 | G15: Taowine | H15: China | I15: China | J15: China | K15: CQ’4 2026
A16: AE | B16: iPhone | C16: V7x | D16: FIFO | E16: Fall’27 | G16: BZ | H16: China | I16: China | J16: China | K16: CQ’4 2026
A17: AE | B17: iPhone | C17: V7x | D17: BGS1 | E17: Fall’27 | G17: JST | H17: China | I17: China | J17: China | K17: CQ’4 2026
A18: AE | B18: iPhone | C18: V7x | D18: BGS2 | E18: Fall’27 | G18: JST | H18: China | I18: China | J18: China | K18: CQ’4 2026
... A33: AE | B33: iPhone | C33: V78 | D33: SPUD1 (Pre) | E33: Fall’27 | G33: LG-PRI | H33: Global | I33: China | J33: China/Global | K33: CQ’4 2026

Sheet AE DFM 2027 New Development Sta
A1: Table 1
A2: CapEx Space | B2: LOB | C2: Program | D2: Station | E2: Launch Timing | F2: Line Count | G2: Vendor | H2: CN/Global | I2: NPI Location | J2: MP Geo Impacted | K2: SPOR Lock Date | L2: Intercept EIH | M2: Trending GSSM Recommendation | N2: Station Resource/Capacity Supportability (APO Fill - Y/N)
A3: AE | B3: Portables | C3: J91a | D3: Putter Assembly | E3: Spring 27 | F3: 12 | G3: Laservall | H3: Global | I3: CN | J3: CN, VN | K3: Done
A4: AE | B4: Portables | C4: K104/K12p | D4: TP-TC Height Measurement | E4: Fall 27 | F4: 3? | G4: Stiwa | H4: Global | I4: CN | J4: CN, VN
A5: AE | B5: Portables | C5: K104/K12p | D5: TP Shim Install | E5: Fall 27 | F5: 3? | G5: Stiwa | H5: Global | I5: CN | J5: CN, VN
A6: AE | B6: Portables | C6: K104/K12p | D6: TP2TC Pre Install and TP Shim AOI | E6: Fall 27 | F6: 3? | G6: Stiwa | H6: Global | I6: CN | J6: CN, VN
A7: AE | B7: Portables | C7: K104/K12p | D7: TP Alignment Screw Fasten | E7: Fall 27 | F7: 3? | G7: Stiwa | H7: Global | I7: CN | J7: CN, VN
A8: AE | B8: Portables | C8: K104/K12p | D8: TP2TC Gap-Offset Measurement | E8: Fall 27 | F8: 3? | G8: Stiwa | H8: Global | I8: CN | J8: CN, VN
A9: AE | B9: Portables | C9: K104/K12p | D9: Flex Assembly | E9: Fall 27 | F9: 3? | G9: Laservall | H9: Global | I9: CN | J9: CN, VN
A10: AE | B10: Audio | C10: B798 | D10: SCUD 3.0 Nozzle to Cap | E10: Fall 27 | G10: ASM | H10: Global | I10: CN | J10: CN, VN , IN | L10: P2
A11: AE | B11: Audio | C11: B798 | D11: SCUD 3.0 Slab Area on Cap | E11: Fall 27 | G11: Laservall | H11: Global | I11: CN | J11: CN, VN , IN | L11: P2
A12: AE | B12: Audio | C12: B798 | D12: UPCR-IR Slab Cure | E12: Fall 27 | G12: ASM | H12: Global | I12: CN | J12: CN, VN , IN | L12: P2
A13: AE | B13: Audio | C13: B798 | D13: PnP + HAF Under Weld Ring Pre-Activate | E13: Fall 27 | G13: ASM | H13: Global | I13: CN | J13: CN, VN , IN | L13: P2
A14: AE | B14: Audio | C14: B798 | D14: UPCR-IR Driver & Actin Module Cure | E14: Fall 27 | G14: ASM | H14: Global | I14: CN | J14: CN, VN , IN | L14: P2
A15: AE | B15: Audio | C15: B798 | D15: Auto Bend Cap Flex | E15: Fall 27 | G15: Delta | H15: Global | I15: CN | J15: CN, VN , IN | L15: P2
A16: AE | B16: Audio | C16: B798 | D16: PnP + HAF SC to CP | E16: Fall 27 | G16: Delta | H16: Global | I16: CN | J16: CN, VN , IN | L16: P2
A17: AE | B17: Audio | C17: B798 | D17: UPCR-IR CP to HSG Cure | E17: Fall 27 | G17: ASM | H17: Global | I17: CN | J17: CN, VN , IN | L17: P2
A18: AE | B18: Audio | C18: B798 | D18: PnP + Press BCF to HSG | E18: Fall 27 | G18: ASM | H18: Global | I18: CN | J18: CN, VN , IN | L18: P2
A19: AE | B19: Audio | C19: B798 | D19: UPCR-IR BCF and TM Cure | E19: Fall 27 | G19: ASM | H19: Global | I19: CN | J19: CN, VN , IN | L19: P2
A20: AE | B20: Audio | C20: B798 | D20: Auto Bend HSG Flex | E20: Fall 27 | G20: Delta | H20: Global | I20: CN | J20: CN, VN , IN | L20: P2
A21: AE | B21: Audio | C21: B798 | D21: UPCR-IR Cap to HSG | E21: Fall 27 | G21: ASM | H21: Global | I21: CN | J21: CN, VN , IN | L21: P2
... A70: AE | B70: Audio | C70: B798 | D70: FATP LSJ Solder Joint AOI | E70: Fall 27 | G70: Laservall | H70: Global | I70: CN | J70: CN, VN | L70: P1
A71: AE | B71: Portables | C71: J91a | D71: Mesa Backlight Press | E71: Spring 27 | F71: 12 | G71: Laservall | H71: Global | I71: CN | J71: CN, VN | L71: TBD
A72: AE | B72: Portables | C72: J91a | D72: TM Press | E72: Spring 27 | F72: 12 | G72: Laservall | H72: Global | I72: CN | J72: CN, VN | L72: TBD

Sheet Y2027 NPI - PRM (Anna) - 4_23v 
A1: Resource Availability for Y2027 NPI Support
A2: SI Name | B2: Resource | C2: Y2026 Loading (Apr’26 ~ Sep’26) | D2: Total Resource (Cut Off Apr wk3) | E2: Resource Occupied for Y2026 Ramp (Apr’26 ~ Sep’26) | F2: Resource Leftover for Y2027 Brand-New Station NPI Build (Apr’26 ~ Sep’26) | G2: # of Stations Type can support (Refer CPT Y2027 RFP) | H2: Station Name can support (Refer CPT Y2027 RFP) | I2: Justification on why resource can support | J2: Space Supportability (Y/N) | K2: Machining Capacity Supportability (Y/N) | L2: Assembly Capacity Supportability (Y/N) | M2: Quality Capacity Supportability (Y/N) | N2: Station Name CANNOT Support (Refer CPT Y2027 RFP) & Justification
A3: PRM | B3: PM | C3: {=SUM(E3:E7)/SUM(D3:D7)} -> 0.80608365 | D3: 47 | E3: 40 | F3: 7 | G3: 1x | H3: So far for iPhone V7x Station ALS-P | I3: Refer to V6x FACTVENT station NPI resourced required as below: PM- 1x ME - 3x EE - 5x | J3: Y | K3: Y | L3: Y | M3: Y | N3: /
A4: PRM | B4: ME | D4: 70 | E4: 61 | F4: 9
A5: PRM | B5: EE | D5: 79 | E5: 62 | F5: 17
A6: PRM | B6: SW | D6: 51 | E6: 43 | F6: 8
A7: PRM | B7: VE | D7: 16 | E7: 6 | F7: 10
A8: Total | D8: {=SUM(D3:D7)} -> 263 | E8: {=SUM(E3:E7)} -> 212 | F8: {=SUM(F3:F7)} -> 51
A9: Loading% | E9: {=E8/D8} -> 0.80608365 | F9: {=F8/D8} -> 0.19391635

Sheet Y2027 NPI - PRM (Anna) - 4_23v1
A1: Y2026 Loading Breakdown (Apr ~ Sep)
A2: SI Name | B2: Items | C2: Portable | D2: Pad | E2: Desktop | F2: Audio | G2: Watch | H2: Phone
A3: PRM | B3: Program | C3: J701/K104/J91a/K11p | D3: J8x7/J9xx/J510 | E3: J775/J873/J883/J83x | F3: B798/B868/B790/B747a/B727 | G3: N23x/N240 | H3: V68/V6X
A4: PRM | B4: Station Name | C4: Snoop/Snoop-c/RC FACT/FACT conveyor | D4: FCT/DFU/SOC | E4: FCT/DFU/SOC | F4: Flex FCT/Flex Mic/FCT | G4: Panel DFU/FCT/GK FCT/BI/Conveyor/Bamboo/Marge&X-talk | H4: Grape/Helios/FACT & VENT /Snoop C
A5: PRM | B5: Station Total Demand | C5: {=SUM(C6:C9)} -> 40 | D5: {=SUM(D6:D9)} -> 23 | E5: {=SUM(E6:E9)} -> 29 | F5: {=SUM(F6:F9)} -> 37 | G5: {=SUM(G6:G9)} -> 24 | H5: {=SUM(H6:H9)} -> 53
A6: PRM | B6: PM | C6: {=2+5} -> 7 | D6: 2 | E6: {=3+1} -> 4 | F6: {=7+2} -> 9 | G6: {=2+2+2} -> 6 | H6: {=8+4} -> 12
A7: PRM | B7: ME | C7: {=5+7} -> 12 | D7: 5 | E7: {=5+2} -> 7 | F7: {=5+3} -> 8 | G7: {=3+2+1} -> 6 | H7: {=10+13} -> 23
A8: PRM | B8: EE | C8: {=1+10} -> 11 | D8: 8 | E8: {=8+2} -> 10 | F8: {=8+1} -> 9 | G8: {=5+1+2} -> 8 | H8: {=6+10} -> 16
A9: PRM | B9: SW | C9: {=1+6+3} -> 10 | D9: 8 | E9: {=6+2} -> 8 | F9: {=10+1} -> 11 | G9: {=3+1} -> 4 | H9: 2
A10: PRM | B10: VE | H10: 6

Sheet Y2027 NPI - PRM (Anna) - 4_23v2
A1: 2027 Idle Resources Name List for ALS_P
B2: Namelist | C2: Position PM/ME/EE/SW/FAE/AE/VE | D2: 2026 Projects Dedicated% | E2: Apple Projects Experiences (Years) | F2: PRM Projects Experiences (Years) | G2: Current Scope at PRM | H2: Location | I2: Expertise
A3: PM
B4: 李泉 | C4: PM | D4: 1 | E4: 12 | F4: 5.6 | I4: Board test and Conveyor
B5: 张望旺 | C5: PM | D5: 1 | E5: 11 | F5: 1.4 | I5: Board test and Conveyor
B6: 李鹏涛 | C6: PM | D6: 1 | E6: 11 | F6: 0.1 | I6: Board test and Conveyor
B7: 陈二鹏 | C7: PM | D7: 0 | E7: 10 | F7: 11.1 | G7: Non-A | H7: Zhuhai | I7: TPM
B8: 高小银 | C8: PM | D8: 1 | E8: 10 | F8: 0.1 | I8: Board test and Conveyor
B9: 孙小伟 | C9: PM | D9: 1 | E9: 10 | F9: 2.9 | I9: Board test and Conveyor
B10: 郑晨光 | C10: PM | D10: 1 | E10: 10 | F10: 2.7 | I10: Board test and Conveyor
B11: 高阳 | C11: PM | D11: 1 | E11: 10 | F11: 4.8 | I11: Board test and Conveyor
B12: 尹昌 | C12: PM | D12: 1 | E12: 10 | F12: 0.5 | I12: Board test and Conveyor
B13: 高楠 | C13: PM | D13: 1 | E13: 10 | F13: 1.3 | I13: Board test and Conveyor
B14: 汤爱苹 | C14: PM | D14: 1 | E14: 10 | F14: 1 | I14: Board test and Conveyor
B15: 周颖 | C15: PM | D15: 1 | E15: 9 | F15: 6.4 | I15: Board test and Conveyor
B16: 陈英武 | C16: PM | D16: 1 | E16: 9 | F16: 8.2 | I16: Board test and Conveyor
B17: 林艳玲 | C17: PM | D17: 1 | E17: 9 | F17: 9 | I17: Board test and Conveyor
B18: 郜继成 | C18: PM | D18: 1 | E18: 8.1 | F18: 8.1 | I18: Board test and Conveyor
B19: 刘雪 | C19: PM | D19: 0.5 | E19: 8 | F19: 8.9 | I19: Board test and Conveyor
... B53: 赖彩连 | C53: PM | D53: 1 | E53: 4 | F53: 3.5 | I53: Board test and Conveyor
B54: 叶文理 | C54: PM | D54: 0 | E54: 3 | F54: 8 | G54: Non-A | H54: Zhuhai | I54: PM/Automation Line
B55: 曹秋香 | C55: PM | D55: 0 | E55: 3 | F55: 3.7 | G55: Non-A | H55: Shanghai | I55: PM/Automation Line
B56: 叶玮 | C56: PM | D56: 0 | E56: 3 | F56: 1.3 | G56: Non-A | H56: Zhuhai | I56: PM/Automation Line
B57: 戴文豪 | C57: PM | D57: 0 | E57: 3 | F57: 4.4 | G57: Non-A | H57: Zhuhai | I57: PM/Testing Equipment
B58: 罗正波 | C58: PM | D58: 1 | E58: 3 | F58: 2.3 | I58: Board test and Conveyor
B59: 马思兰 | C59: PM | D59: 1 | E59: 3 | F59: 0.8 | I59: Board test and Conveyor
B60: 廖昌锋 | C60: PM | D60: 1 | E60: 3 | F60: 2.7 | I60: Board test and Conveyor
B61: 唐淑婷 | C61: PM | D61: 1 | E61: 3 | F61: 1.7 | I61: Board test and Conveyor
B62: 翦海怡 | C62: PM | D62: 1 | E62: 3 | F62: 0.5 | I62: Board test and Conveyor
B63: 曲晓雨 | C63: PM | D63: 1 | E63: 3 | F63: 3.9 | I63: Board test and Conveyor
B64: 武迎新 | C64: PM | D64: 0.5 | E64: 2 | F64: 0.1 | I64: Board test and Conveyor
B65: 赵鑫月 | C65: PM | D65: 0.7 | E65: 2 | F65: 2.2 | I65: Board test and Conveyor
B66: 田祖棋 | C66: PM | D66: 0.8 | E66: 2 | F66: 2.7 | I66: Board test and Conveyor
B67: 刘华东 | C67: PM | D67: 0.8 | E67: 2 | F67: 2.4 | I67: Board test and Conveyor
B68: 卢轶桐 | C68: PM | D68: 1 | E68: 2 | F68: 0.1 | I68: Board test and Conveyor
B69: 文慧芳 | C69: PM | D69: 1 | E69: 2 | F69: 1.7 | I69: Board test and Conveyor
... B77: 田国源 | C77: PM | D77: 1 | E77: 1 | F77: 0.2 | I77: Board test and Conveyor
B78: 钟冠群 | C78: PM | D78: 0 | E78: 0.5 | F78: 4.1 | G78: Non-A | H78: Shanghai | I78: PM/Automation Line
B79: 郑礼海 | C79: PM | D79: 0 | E79: 0.5 | F79: 2.3 | G79: Non-A | H79: Zhuhai | I79: PM/Automation Line
B80: 杨未央 | C80: PM | D80: 0.8 | E80: 0.4 | F80: 0.4 | I80: Board test and Conveyor
B81: 李兴明 | C81: PM | D81: 1 | E81: 0.4 | F81: 0.4 | I81: Board test and Conveyor
B82: 许巧玲 | C82: PM | D82: 0.5 | E82: 0 | F82: 0.1 | I82: Board test and Conveyor
A83: ME
B84: 颜锋 | C84: ME | D84: 1 | E84: 15 | F84: 6.9 | I84: /
B85: 朱隆贵 | C85: ME | D85: 1 | E85: 12 | F85: 1.5 | I85: Board test and Conveyor
B86: 吕仕坚 | C86: ME | D86: 0 | E86: 11 | F86: 0.4 | G86: Non-A | H86: Zhuhai | I86: Testing Equipment and Automation Line
B87: 刘小溪 | C87: ME | D87: 1 | E87: 11 | F87: 5.6 | I87: /
B88: 李永祥 | C88: ME | D88: 1 | E88: 10 | F88: 11.3 | I88: Conveyor
B89: 汪伟 | C89: ME | D89: 0.9 | E89: 10 | F89: 1.6 | I89: Board test and Conveyor
B90: 周守家 | C90: ME | D90: 0.9 | E90: 10 | F90: 5.4 | I90: Conveyor
B91: 张浩 | C91: ME | D91: 0 | E91: 9 | F91: 0.8 | G91: Non-A | H91: Zhuhai | I91: Testing Equipment and Automation Line
B92: 刘振伟 | C92: ME | D92: 1 | E92: 9 | F92: 2.6 | I92: Conveyor
B93: 莫宗杰 | C93: ME | D93: 1 | E93: 9 | F93: 6.4 | I93: Board test
B94: 陈龙 | C94: ME | D94: 0 | E94: 8 | F94: 8.8 | G94: Non-A | H94: Zhuhai | I94: Testing Equipment and Automation Line
B95: 黄国华 | C95: ME | D95: 1 | E95: 8 | F95: 2.4 | I95: Board test
B96: 许耀杰 | C96: ME | D96: 1 | E96: 7 | F96: 8.6 | I96: Conveyor
B97: 李灵灵 | C97: ME | D97: 1 | E97: 7 | F97: 4.1 | I97: Board test and Conveyor
B98: 黄奕鸿 | C98: ME | D98: 1 | E98: 7 | F98: 4.1 | I98: Board test and Conveyor
B99: 詹佳佳 | C99: ME | D99: 1 | E99: 7 | F99: 1.9 | I99: Board test and Conveyor
B100: 陈晓光 | C100: ME | D100: 1 | E100: 6.5 | F100: 2.6 | I100: Conveyor
B101: 吴恩海 | C101: ME | D101: 1 | E101: 6 | F101: 1.4 | I101: Conveyor
B102: 刘耀平 | C102: ME | D102: 1 | E102: 6 | F102: 8.4 | I102: Board test
B103: 何启豪 | C103: ME | D103: 1 | E103: 6 | F103: 4
B104: 贺云 | C104: ME | D104: 1 | E104: 6 | F104: 1.3
B105: 于四海 | C105: ME | D105: 1 | E105: 6 | F105: 1.1 | I105: /
B106: 王磊 | C106: ME | D106: 1 | E106: 5.9 | F106: 5.9 | I106: Board test
B107: 熊光谱 | C107: ME | D107: 0 | E107: 5.6 | F107: 1.6 | G107: Non-A | H107: Zhuhai | I107: Testing Equipment and Automation Line
B108: 蔡名威 | C108: ME | D108: 1 | E108: 5 | F108: 5
B109: 杨胜利 | C109: ME | D109: 1 | E109: 5 | F109: 0.1
B110: 翟德沛 | C110: ME | D110: 1 | E110: 5 | F110: 1.5
B111: 蒋家文 | C111: ME | D111: 1 | E111: 5 | F111: 0.9 | I111: /
B112: 田海翔 | C112: ME | D112: 1 | E112: 5 | F112: 1.8 | I112: Board test and Conveyor
B113: 卢敏兴 | C113: ME | D113: 1 | E113: 4.7 | F113: 4.7 | I113: Board Test
B114: 陈国栋 | C114: ME | D114: 0.9 | E114: 4.5 | F114: 2.6 | I114: Conveyor
B115: 黄田孝 | C115: ME | D115: 1 | E115: 4.5 | F115: 4.5 | I115: Board Test
B116: 刘露棣 | C116: ME | D116: 1 | E116: 4.1 | F116: 4.1 | I116: Conveyor
B117: 张建德 | C117: ME | D117: 1 | E117: 4.1 | F117: 4.1 | I117: Board test
B118: 杨帆 | C118: ME | D118: 1 | E118: 4.1 | F118: 4.1 | I118: Board Test
B119: 陈胜乐 | C119: ME | D119: 1 | E119: 4 | F119: 3.1
B120: 郑胜明 | C120: ME | D120: 1 | E120: 4 | F120: 1.4
B121: 高辉 | C121: ME | D121: 1 | E121: 4 | F121: 1.2 | I121: /
B122: 李兴聪 | C122: ME | D122: 1 | E122: 4 | F122: 2.7 | I122: Conveyor
B123: 王玮 | C123: ME | D123: 1 | E123: 4 | F123: 2.6 | I123: Conveyor
B124: 王晓宁 | C124: ME | D124: 1 | E124: 3.6 | F124: 3.6 | I124: Board Test
B125: 杨梓熙 | C125: ME | D125: 0 | E125: 3 | F125: 3.1 | G125: Non-A | H125: Zhuhai | I125: Testing Equipment and Automation Line
B126: 鲁秋瑞 | C126: ME | D126: 1 | E126: 3 | F126: 0.7 | I126: Board test
B127: 黄显壮 | C127: ME | D127: 0 | E127: 3 | F127: 0.4 | G127: Non-A | H127: Zhuhai | I127: Testing Equipment and Automation Line
B128: 杨锦杰 | C128: ME | D128: 1 | E128: 3 | F128: 3.5 | I128: Board test and Conveyor
B129: 吴信会 | C129: ME | D129: 1 | E129: 3 | F129: 3.4 | I129: Board test and Conveyor
B130: 陈兴顺 | C130: ME | D130: 1 | E130: 3 | F130: 6 | I130: Board test and Conveyor
B131: 戴林飞 | C131: ME | D131: 1 | E131: 3 | F131: 2.8 | I131: Board test and Conveyor
B132: 朱长乐 | C132: ME | D132: 1 | E132: 2.7 | F132: 2.7 | I132: Board Test
B133: 王建祥 | C133: ME | D133: 1 | E133: 2.5 | F133: 2.5 | I133: Board Test
B134: 张永亮 | C134: ME | D134: 1 | E134: 2.5 | F134: 2.5 | I134: Board Test
B135: 黄胜彬 | C135: ME | D135: 1 | E135: 2.5 | F135: 2.5 | I135: Board Test
B136: 吴伟杰 | C136: ME | D136: 1 | E136: 2.4 | F136: 2.4 | I136: Board Test
B137: 吴亮主 | C137: ME | D137: 1 | E137: 2.2 | F137: 2.2
B138: 伍海鱼 | C138: ME | D138: 0 | E138: 2 | F138: 2 | G138: Phone V6x Helios | H138: Zhuhai | I138: Testing Equipment and Automation Line
B139: 陈雪刚 | C139: ME | D139: 0 | E139: 1.7 | F139: 1.7 | G139: Non-A | H139: Zhuhai | I139: Testing Equipment and Automation Line
B140: 陆飞 | C140: ME | D140: 1 | E140: 1.6 | F140: 1.6
...

Sheet Y2027 NPI - Innorev (Fiona) - R
A1: Resource Availability for Y2027 NPI Support
A2: SI Name | B2: Resource | C2: Y2026 Loading (Apr’26 ~ Sep’26) | D2: Total Resource (Cut Off Apr wk3) | E2: Resource Occupied for Y2026 Ramp (Apr’26 ~ Sep’26) | F2: Resource Leftover for Y2027 Brand-New Station NPI Build (Apr’26 ~ Sep’26) | G2: # of Stations Type can support (Refer CPT Y2027 RFP) | H2: Station Name can support (Refer CPT Y2027 RFP) | I2: Justification on why resource can support | J2: Space Supportability (Y/N) | K2: Machining Capacity Supportability (Y/N) | L2: Assembly Capacity Supportability (Y/N) | M2: Quality Capacity Supportability (Y/N) | N2: Station Name CANNOT Support (Refer CPT Y2027 RFP) & Justification
A3: Innorev | B3: PM | C3: {=SUM(E3:E10)/SUM(D3:D10)} -> 0.51492537 | D3: 24 | E3: 8 | F3: {=D3-E3} -> 16 | G3: 2x, conveyor and standalone with a design assumptions i.e similar as Scarlet/ASL-P/DVI/IMU conveyor and SA standalone stations. | H3: iPhone V7x Station ALS-P Conveyor, Odin Conveyor, DCR/OS Tests, IQC AA stations. iPad J8x7 Station DVI Conveyor Watch N25x Station FACT21&Vent2 Conveyor, Conveyor Cyan Rotary Audio B798 station All in One Case, Open Short, IMU Camera. | I3: Refer to Mistral DVI Conveyor,V6x SA standalone and other QT stations,we had experience in similar complexity, NPI resourced required as below: IPhone V7x ALS-P Conveyor: ME - 2x EE - 2x TPM -2x OSS - 2x IPhone V7x DCR /OS test and IQC AA stations: ME - 2x EE - 1x TPM - 1x OSS - 2x IPad J8x7 DVI Conveyor: ME - 2x EE - 2x TPM - 1x OSS - 2x Watch N25x FACT21&VANT2 Conveyor: ME - 3x EE - 3x TPM - 1x OSS - 2x Watch N25x Conveyor Cyan: ME - 3x EE - 3x TPM - 1x OSS - 2x Audio B798 All in One Case and Open Short ME - 1x EE - 1x TPM - 1x OSS - 1x Audio B798 IMU Camera ME - 2x EE - 1x TPM - 1x OSS - 1x | J3: Y | K3: Y | L3: Y | M3: Y | N3: 1. IPhone V7x Station Odin Conveyor-SQE limiitation.
A4: Innorev | B4: ME | D4: 78 | E4: 11 | F4: {=D4-E4} -> 67
A5: Innorev | B5: EE | D5: 29 | E5: 7 | F5: {=D5-E5} -> 22
A6: Innorev | B6: SW | D6: 0 | E6: 0 | F6: {=D6-E6} -> 0
A7: Innorev | B7: FAE | D7: 9 | E7: 4 | F7: {=D7-E7} -> 5
A8: Innorev | B8: Assembly | D8: 208 | E8: 140 | F8: {=D8-E8} -> 68
A9: Innorev | B9: Debug | D9: 32 | E9: 20 | F9: {=D9-E9} -> 12
A10: Innorev | B10: Quality | D10: 22 | E10: 17 | F10: {=D10-E10} -> 5

Sheet Y2027 NPI - Innorev (Fiona) - Y
A1: Y2026 Loading Breakdown (Apr ~ Sep)
A2: SI Name | B2: Items | C2: Portable | D2: Pad | E2: Audio | F2: Watch | G2: Phone
A3: Innorev | B3: Program | C3: J91a | D3: J510 | E3: B868/B790 | F3: N23x | G3: V6x/Mistral
A4: Innorev | B4: Station Name | C4: Button/CBT/Trackpad Force/DVI/QT0/USBC/QT1/SWDL/Actuation/Impedance | D4: ALS Cal/CCB/Freyr/DVI/ISD/QT1/CT1/Janus | E4: Kinneret/Grid Flare/Shipping setting/All in one/SA-QT2/Burn in/SA-QT1/QT1/FWDL/Smart Charging/Gatekeeper | F4: ALS-COMBO/Magnetizer/InterConnect/Reflow line/Loading/Unloading | G4: Jasmine/Magnolia/IMU Conveyor/DVI Conveyor/ALS-P/Scarlet/Scarlet IMU/Alpha/Vent2/ISD
A5: Innorev | B5: Station Total Demand | C5: 10 | D5: 8 | E5: 11 | F5: 6 | G5: 10
A6: Innorev | B6: PM | C6: 3 | D6: 7 | E6: 4 | F6: 2 | G6: 8
A7: Innorev | B7: ME | C7: 10 | D7: 16 | E7: 11 | F7: 8 | G7: 33
A8: Innorev | B8: EE | C8: 2 | D8: 6 | E8: 4 | F8: 5 | G8: 12
A9: Innorev | B9: SW | C9: 0 | D9: 0 | E9: 0 | F9: 0 | G9: 0
A10: Innorev | B10: FAE | C10: 1 | D10: 3 | E10: 1 | F10: 1 | G10: 3
A11: Innorev | B11: Assembly | C11: 7 | D11: 58 | E11: 33 | F11: 22 | G11: 88
A12: Innorev | B12: Debug | C12: 1 | D12: 9 | E12: 5 | F12: 3 | G12: 14
A13: Innorev | B13: Quality | C13: 2 | D13: 6 | E13: 3 | F13: 1 | G13: 10

Sheet Y2027 NPI - JLK (Sean) - Resour
A1: Resource Availability for Y2027 NPI Support
A2: SI Name | B2: Resource | C2: Y2026 Loading (Apr’26 ~ Sep’26) | D2: Total Resource (Cut Off Apr wk3) | E2: Resource Occupied for Y2026 Ramp (Apr’26 ~ Sep’26) | F2: Resource Leftover for Y2027 Brand-New Station NPI Build (Apr’26 ~ Sep’26) | G2: # of Stations Type can support (Refer CPT Y2027 RFP) | H2: Station Name can support (Refer CPT Y2027 RFP) | I2: Justification on why resource can support | J2: Space Supportability (Y/N) | K2: Machining Capacity Supportability (Y/N) | L2: Assembly Capacity Supportability (Y/N) | M2: Quality Capacity Supportability (Y/N) | N2: Station Name CANNOT Support (Refer CPT Y2027 RFP) & Justification
A3: JLK | B3: PM | C3: {=SUM(E3:E10)/SUM(D3:D10)} -> 0.778125 | D3: 15 | E3: 11 | F3: {=D3-E3} -> 4 | G3: 7x | H3: iPhone V7x Station SA-Barbie iPhone V7x Station Odin Conveyor iPhone V7x Station ALS-P Conveyor iPad J8x7 station DVI Conveyor Audio B798 Station Touch Conveyor Audio B798 Station Force Conveyor Audio B798 Station FACT Conveyor | I3: Refer to V6x SA-Ringo, V6x Odin + Clematis, V6x ALS-P, V6x DVI, B790 Touch, FACT, Force station in similar complexity, NPI resourced required as below: ME - 12x EE - 5x SW- 4x | J3: Y | K3: Y | L3: Y | M3: Y | N3: Watch N25x Station FACT & Vent Conveyor - Resource limitation & Watch N25x Station Cyan Conveyor - Resource limitation Portable 91a Station caramel Conveyor—Tie P2 validation schedule, cannot catch up build date
A4: JLK | B4: ME | D4: {=12+2+12+4} -> 30 | E4: 17 | F4: {=D4-E4} -> 13
A5: JLK | B5: EE | D5: 12 | E5: 8 | F5: {=D5-E5} -> 4
A6: JLK | B6: SW | D6: 8 | E6: 5 | F6: {=D6-E6} -> 3
A7: JLK | B7: FAE | D7: 25 | E7: 20 | F7: {=D7-E7} -> 5
A8: JLK | B8: Assembly | D8: 150 | E8: 116 | F8: {=D8-E8} -> 34
A9: JLK | B9: Debug | D9: 60 | E9: 55 | F9: {=D9-E9} -> 5
A10: JLK | B10: Quality | D10: 20 | E10: 17 | F10: {=D10-E10} -> 3

Sheet Y2027 NPI - JLK (Sean) - Y2026 
A1: Y2026 Loading Breakdown (Apr ~ Sep)
A2: SI Name | B2: Items | C2: Portable | D2: Pad | E2: Audio | F2: Watch | G2: Phone
B3: Program | C3: K11P | D3: J510/J581/B001 | E3: B790/B868 | F3: N24x | G3: V6x/V68
B4: Station Name | C4: KB PEM/ALS CAL/ALS_X-talk/Grape/ISD Standalone | D4: Grape Test/ALS CAL/System Test Standalone | E4: Touch Cal/Prox/Regia/LED Standalone | F4: Grape | G4: FACT/ALS/A-AMAI/Hydros/Barbie Standalone FACT & Vent /DVI/Grape Conveyor
B5: Station Total Demand | C5: 111 | D5: {=4+54} -> 58 | E5: {=120+12*4+8} -> 176 | F5: 15 | G5: {=189+219} -> 408
B6: PM | C6: 2 | D6: 1 | E6: 2 | F6: 1 | G6: 3
B7: ME | C7: 2 | D7: 1 | E7: 2 | F7: 1 | G7: 3
B8: EE | C8: 2 | D8: 1 | E8: 1 | F8: 1 | G8: 2
B9: SW | C9: 1 | D9: 0 | E9: 1 | F9: 0 | G9: 2
B10: FAE | C10: 3 | D10: 2 | E10: 1 | F10: 1 | G10: 10
B11: Assembly | C11: 13 | D11: 3 | E11: 5 | F11: 2 | G11: {=38+25} -> 63
B12: Debug | C12: 5 | D12: 2 | E12: 2 | F12: 1 | G12: {=18+15} -> 33
B13: Quality | C13: 2 | D13: 1 | E13: 1 | F13: 1 | G13: 10

Sheet Y2027 NPI - JLK IN 5_18v - Reso
A1: Resource Availability for Y2027 NPI Support
A2: SI Name | B2: Resource | C2: Y2026 Loading (Apr’26 ~ Sep’26) | D2: Total Resource (Cut Off May wk1) | E2: Resource Occupied for Y2026 Ramp (Apr’26 ~ Sep’26) | F2: Resource Leftover for Y2027 Brand-New Station NPI Build (Apr’26 ~ Sep’26) | G2: # of Stations Type can support (Refer CPT Y2027 RFP) | H2: Station Name can support (Refer CPT Y2027 RFP) | I2: Justification on why resource can support | J2: Space Supportability (Y/N) | K2: Machining Capacity Supportability (Y/N) | L2: Assembly Capacity Supportability (Y/N) | M2: Quality Capacity Supportability (Y/N)
A3: JLK IN | B3: PM | C3: {=SUM(E3:E10)/SUM(D3:D10)} -> 0.70731707 | D3: 14 | E3: 10 | F3: {=D3-E3} -> 4 | G3: 3 | H3: iPhone V7x Station SA-Barbie iPhone V7x Station Odin Conveyor iPhone V7x Station ALS-P Conveyor Audio B798 Station Touch Conveyor Audio B798 Station Force Conveyor Audio B798 Station FACT Conveyor | I3: JLK teams highly experienced with both standalone and conveyor stations like Barbie, SA-Ringo, DVI, Clematis, Odin, ALS-P, Wisteria, ALS X-Talk, Vent, Fact, Grape, Voyager. | J3: Y | K3: Y | L3: Y | M3: Y
A4: JLK IN | B4: ME | D4: 21 | E4: 12 | F4: {=D4-E4} -> 9
A5: JLK IN | B5: EE | D5: 10 | E5: 6 | F5: {=D5-E5} -> 4
A6: JLK IN | B6: SW | D6: 12 | E6: 7 | F6: {=D6-E6} -> 5
A7: JLK IN | B7: FAE | D7: 5 | E7: 4 | F7: {=D7-E7} -> 1
A8: JLK IN | B8: Assembly | D8: 91 | E8: 65 | F8: {=D8-E8} -> 26
A9: JLK IN | B9: Debug | D9: 44 | E9: 35 | F9: {=D9-E9} -> 9
A10: JLK IN | B10: Quality | D10: 8 | E10: 6 | F10: {=D10-E10} -> 2

Sheet Y2027 NPI - JLK IN 5_18v - Y202
A1: Y2027 RFP Breakdown
A2: SI Name | B2: Items | C2: Portable | D2: Pad | E2: Audio | F2: Watch | G2: Phone
A3: JLK IN | B3: Program | C3: - | D3: - | E3: - | F3: - | G3: V7x
A4: JLK IN | B4: Station Name | C4: - | D4: - | E4: - | F4: - | G4: ALS-P conveyor, Odin conveyor, SA-Barbie
A5: JLK IN | B5: Station Total Demand | C5: - | D5: - | E5: - | F5: - | G5: 3
A6: JLK IN | B6: PM | C6: - | D6: - | E6: - | F6: - | G6: 3
A7: JLK IN | B7: ME | C7: - | D7: - | E7: - | F7: - | G7: 3
A8: JLK IN | B8: EE | C8: - | D8: - | E8: - | F8: - | G8: 3
A9: JLK IN | B9: SW | C9: - | D9: - | E9: - | F9: - | G9: 2
A10: JLK IN | B10: FAE | C10: - | D10: - | E10: - | F10: - | G10: 2
A11: JLK IN | B11: Assembly | C11: - | D11: - | E11: - | F11: - | G11: 10
A12: JLK IN | B12: Debug | C12: - | D12: - | E12: - | F12: - | G12: 9
A13: JLK IN | B13: Quality | C13: - | D13: - | E13: - | F13: - | G13: 2

Sheet Y2027 NPI - VVDN IN 5_18 - Reso
A1: Resource Availability for Y2027 NPI Support
A2: SI Name | B2: Resource | C2: Y2026 Loading (Apr’26 ~ Sep’26) | D2: Total Resource (Cut Off May wk1) | E2: Resource Occupied for Y2026 Ramp (Apr’26 ~ Sep’26) | F2: Resource Leftover for Y2027 Brand-New Station NPI Build (Apr’26 ~ Sep’26) | G2: # of Stations Type can support (Refer CPT Y2027 RFP) | H2: Station Name can support (Refer CPT Y2027 RFP) | I2: Justification on why resource can support | J2: Space Supportability (Y/N) | K2: Machining Capacity Supportability (Y/N) | L2: Assembly Capacity Supportability (Y/N) | M2: Quality Capacity Supportability (Y/N)
A3: VVDN | B3: PM | C3: {=SUM(E3:E10)/SUM(D3:D10)} -> 0.73684211 | D3: 10 | E3: 8 | F3: {=D3-E3} -> 2 | G3: 2 | H3: Y, 2500 Sqft. In Delh (North)i and 16,200 Sqft. In Pollachi (South) | J3: Y, 2500 Sqft. In Delh (North)i and 16,200 Sqft. In Pollachi (South) | K3: Y, 8x inhouse and 15x with Sub-tier | L3: Yes, by aligning operators and production heads | M3: Yes, 2x available (Hiring for additional in progress)
A4: VVDN | B4: ME | D4: 20 | E4: 15 | F4: {=D4-E4} -> 5
A5: VVDN | B5: EE | D5: 32 | E5: 25 | F5: {=D5-E5} -> 7
A6: VVDN | B6: SW | D6: 15 | E6: 9 | F6: {=D6-E6} -> 6
A7: VVDN | B7: FAE | F7: {=D7-E7} -> 0
A8: VVDN | B8: Assembly | D8: 30 | E8: 20 | F8: {=D8-E8} -> 10
A9: VVDN | B9: Debug | D9: 15 | E9: 12 | F9: {=D9-E9} -> 3
A10: VVDN | B10: Quality | D10: 11 | E10: 9 | F10: {=D10-E10} -> 2

Sheet Y2027 NPI - VVDN IN 5_18 - Y202
A1: Y2027 RFP Breakdown
A2: SI Name | B2: Items | C2: Phone | D2: Phone | E2: Phone
A3: VVDN | B3: Program | C3: V7X | D3: V7X | E3: V7X
A4: VVDN | B4: Station Name | C4: Odin Conveyor | D4: ALS Conveyor | E4: Chronos
A5: VVDN | B5: Station Total Demand | C5: New | D5: New | E5: New
A6: VVDN | B6: PM | C6: 0.5 | D6: 0.5 | E6: 1
A7: VVDN | B7: ME | C7: 2 | D7: 2 | E7: 2
A8: VVDN | B8: EE | C8: 1 | D8: 1 | E8: 1
A9: VVDN | B9: SW | C9: 2 | D9: 2 | E9: 2
A10: VVDN | B10: FAE
A11: VVDN | B11: Quality | C11: 1 | D11: 1 | E11: 1
A12: VVDN | B12: Assembly (Leads + Operator) | C12: 10 | D12: 10 | E12: 10
A13: VVDN | B13: Debug | C13: 2 | D13: 2 | E13: 2
A14: VVDN | B14: Quality | C14: 0 | D14: 0 | E14: 0

Sheet Y2027 NPI - Cencorp (Rick) - Re
A1: Resource Availability for Y2027 NPI Support
A2: SI Name | B2: Resource | C2: Y2026 Loading (Apr’26 ~ Sep’26) | D2: Total Resource (Cut Off Apr wk3) | E2: Resource Occupied for Y2026 Ramp (Apr’26 ~ Sep’26) | F2: Resource Leftover for Y2027 Brand-New Station NPI Build (Apr’26 ~ Sep’26) | G2: Cencorp Plan Resource Allocated to Y2027 RFP (Apr’26 ~ Sep’26) | H2: Leftover Resource after allocated to Y2027 RFP | I2: # of Stations Type can support (Refer CPT Y2027 RFP) | J2: Station Name can support (Refer CPT Y2027 RFP) | K2: Justification on why resource can support | L2: Space Supportability (Y/N) | M2: Machining Capacity Supportability (Y/N) | N2: Assembly Capacity Supportability (Y/N) | O2: Quality Capacity Supportability (Y/N) | P2: Station Name CANNOT Support (Refer CPT Y2027 RFP) & Justification
A3: Cencorp | B3: PM/TPM | C3: {=SUM(E3:E7)/SUM(D3:D7)} -> 0.49079755 | D3: 31 | E3: {=SUM('Y2027 NPI - Cencorp (Rick) - Y1'!C6:G6)} -> 15 | F3: {=D3-E3} -> 16 | G3: {=SUM('Y2027 NPI - Cencorp (Rick) - Y2'!C6:J6)} -> 8.5 | H3: {=F3-G3} -> 7.5 | I3: Cencorp can take maximum 8x RFP stations as they are currently engaged (see column J details). Any additional RFP will be medium-high risk to Cencorp according to their leftover engineering resources (see column H details) | J3: J807/J830 iPad DVI N25x Watch Bamboo FACT N25x Watch Bamboo Cyan V7x iPhone Odin V7x iPhone ALS-P V7x iPhone SA Barbie K12P Portable Seasalt K104 Portable Volga | K3: 1. Total leftover PM&RD resource for brand-new stations is about 49% 2. Leftover engineering resources allocation matrix plan showing able to support current engaged 8x RFP stations | L3: Taicang Total：6000 Everest MP: 2000 Everest NPI: 500 Others: 2000 Leftover: 1500 Zhuhai Total：3500 Everest MP: 2100 Everest NPI:300 Others: 800 Leftover: 300 | M3: Y | N3: Y | O3: Y
A4: Cencorp | B4: ME | D4: 43 | E4: {=SUM('Y2027 NPI - Cencorp (Rick) - Y1'!C7:G7)} -> 21.5 | F4: {=D4-E4} -> 21.5 | G4: {=SUM('Y2027 NPI - Cencorp (Rick) - Y2'!C7:J7)} -> 15 | H4: {=F4-G4} -> 6.5
A5: Cencorp | B5: EE | D5: 36 | E5: {=SUM('Y2027 NPI - Cencorp (Rick) - Y1'!C8:G8)} -> 20 | F5: {=D5-E5} -> 16 | G5: {=SUM('Y2027 NPI - Cencorp (Rick) - Y2'!C8:J8)} -> 12 | H5: {=F5-G5} -> 4
A6: Cencorp | B6: SW | D6: 20 | E6: {=SUM('Y2027 NPI - Cencorp (Rick) - Y1'!C9:G9)} -> 5 | F6: {=D6-E6} -> 15 | G6: {=SUM('Y2027 NPI - Cencorp (Rick) - Y2'!C9:J9)} -> 3.5 | H6: {=F6-G6} -> 11.5
A7: Cencorp | B7: FAE | D7: 33 | E7: {=SUM('Y2027 NPI - Cencorp (Rick) - Y1'!C10:G10)} -> 18.5 | F7: {=D7-E7} -> 14.5 | G7: {=SUM('Y2027 NPI - Cencorp (Rick) - Y2'!C10:J10)} -> 10 | H7: {=F7-G7} -> 4.5
A8: Cencorp | B8: Assembly | C8: {=SUM(E8:E9)/SUM(D8:D9)} -> 0.66237113 | D8: 268 | E8: {=SUM('Y2027 NPI - Cencorp (Rick) - Y1'!C11:G11)} -> 180 | F8: {=D8-E8} -> 88 | G8: {=SUM('Y2027 NPI - Cencorp (Rick) - Y2'!C11:J11)} -> 40 | H8: {=F8-G8} -> 48
A9: Cencorp | B9: Debug | D9: 120 | E9: {=SUM('Y2027 NPI - Cencorp (Rick) - Y1'!C12:G12)} -> 77 | F9: {=D9-E9} -> 43 | G9: {=SUM('Y2027 NPI - Cencorp (Rick) - Y2'!C12:J12)} -> 19 | H9: {=F9-G9} -> 24
A10: Cencorp | B10: Quality | C10: {=SUM(E10)/SUM(D10)} -> 0.66 | D10: 25 | E10: {=SUM('Y2027 NPI - Cencorp (Rick) - Y1'!C13:G13)} -> 16.5 | F10: {=D10-E10} -> 8.5 | G10: {=SUM('Y2027 NPI - Cencorp (Rick) - Y2'!C13:J13)} -> 5.5 | H10: {=F10-G10} -> 3
C11: {=SUM(E11)/SUM(D11)} -> 0.61371528 | D11: {=SUM(D3:D10)} -> 576 | E11: {=SUM(E3:E10)} -> 353.5 | F11: {=SUM(F3:F10)} -> 222.5 | G11: {=SUM(G3:G10)} -> 113.5 | H11: {=SUM(H3:H10)} -> 109

Sheet Y2027 NPI - Cencorp (Rick) - Y2
A1: Y2027 RFP Breakdown
A2: SI Name | B2: Items | C2: Portable | D2: Portable | E2: Pad | F2: Watch | G2: Watch | H2: Phone | I2: Phone | J2: Phone
A3: Cencorp | B3: Program | C3: K12p | D3: K104 | E3: J807/J830 | F3: N25x | G3: N25x | H3: V7x | I3: V7x | J3: V7x
A4: Cencorp | B4: Station Name | C4: Seasalt | D4: Volga | E4: DVI | F4: Bamboo FACT | G4: Bamboo Cyan | H4: Odim | I4: ALS-P | J4: SA Barbie
A5: Cencorp | B5: Engagement Status (existing, new) | C5: existing | D5: existing | E5: new | F5: new | G5: new | H5: new | I5: new | J5: new
A6: Cencorp | B6: PM | C6: 2.5 | D6: 1.5 | E6: 1 | F6: 0.5 | G6: 0.5 | H6: 0.5 | I6: 1 | J6: 1
A7: Cencorp | B7: ME | C7: 3 | D7: 3 | E7: 2 | F7: 1 | G7: 1 | H7: 1 | I7: 3 | J7: 1
A8: Cencorp | B8: EE | C8: 3 | D8: 3 | E8: 1 | F8: 0.7 | G8: 0.3 | H8: 1 | I8: 2 | J8: 1
A9: Cencorp | B9: SW | C9: 0.5 | D9: 0.5 | E9: 0.5 | F9: 0.3 | G9: 0.2 | H9: 0.5 | I9: 0.5 | J9: 0.5
A10: Cencorp | B10: FAE | C10: 2.5 | D10: 1.5 | E10: 1 | F10: 0.5 | G10: 0.5 | H10: 1 | I10: 2 | J10: 1
A11: Cencorp | B11: Assembly | C11: 13 | D11: 8 | E11: 4 | F11: 2 | G11: 5 | H11: 2 | I11: 4 | J11: 2
A12: Cencorp | B12: Debug | C12: 8 | D12: 5 | E12: 1 | F12: 1 | G12: 1 | H12: 1 | I12: 1 | J12: 1
A13: Cencorp | B13: Quality | C13: 1.5 | D13: 1 | E13: 0.5 | F13: 0.5 | G13: 0.5 | H13: 0.5 | I13: 0.5 | J13: 0.5

Sheet Y2027 NPI - Cencorp (Rick) - Y1
A1: Y2026 MP Loading Breakdown (Apr ~ Sep)
A2: SI Name | B2: Items | C2: Portable | D2: Pad | E2: Audio | F2: Watch | G2: Phone
A3: Cencorp | B3: Program | C3: J700 / K11p / J91A/ J701 | F3: N23x | G3: V68/V6x
A4: Cencorp | B4: Station Name | C4: Chocolate Seasalt Caramel Nile | F4: Bamboo 2.0 | G4: V68 Magnolia Plus XDXT Hydros Barbie T/V/Salvage V6x Jasmine Clematis Magnolia DVI Barbie V68/V6x MLB AP Stations
A5: Cencorp | B5: Station Total Demand | C5: SeaSalt PRB x 2 SeaSalt PVT x 1 Caramel OVB x1 Nile MP x 4 | F5: Bamboo 2.0 x 4 | G5: V68 NB x 123 RF x 80 V6x NB x 14 RF x 159 V6x/V68 MLB AP NB x 600
A6: Cencorp | B6: PM | C6: 6 | F6: 1 | G6: 8
A7: Cencorp | B7: ME | C7: 8.5 | F7: 3 | G7: 10
A8: Cencorp | B8: EE | C8: 9 | F8: 2 | G8: 9
A9: Cencorp | B9: SW | C9: 1 | F9: 1 | G9: 3
A10: Cencorp | B10: FAE | C10: 7.5 | F10: 1 | G10: 10
A11: Cencorp | B11: Assembly | C11: 48 | F11: {=13*3} -> 39 | G11: 93
A12: Cencorp | B12: Debug | C12: 13 | F12: 12 | G12: 52
A13: Cencorp | B13: Quality | C13: 5 | F13: 2 | G13: 9.5

Sheet Y2027 NPI - Cencorp (Rick) - Y3
A1: Y2026 MP Matrix
A2: Project | B2: PM | C2: ME | D2: EE | E2: SW | F2: FAE | G2: Quality
A3: Magnolia Plus | B3: 1 | C3: 2 | D3: 2 | E3: 1 | F3: 3 | G3: 2
A4: XDXT | B4: 1 | C4: 1 | D4: 1 | F4: 1 | G4: 1
A5: Hydros | B5: 1 | C5: 1 | D5: 1 | F5: 1 | G5: 1
A6: Barbie T/V | B6: 1 | C6: 1 | D6: 1 | E6: 0.5 | F6: 0.5 | G6: 2
A7: Jasmine | B7: 0.5 | C7: 0.5 | D7: 0.5 | F7: 0.5 | G7: 1
A8: Clematis | B8: 0.5 | C8: 0.5 | D8: 0.5 | F8: 0.5 | G8: 1
A9: Magnolia | B9: 0.5 | C9: 0.5 | D9: 0.5 | F9: 0.5 | G9: 1
A10: DVI | B10: 0.5 | C10: 0.5 | D10: 0.5 | E10: 1 | F10: 0.5 | G10: 1
A11: Barbie | B11: 0.5 | C11: 0.5 | D11: 0.5 | E11: 0.5 | F11: 0.5 | G11: 1
A12: MLB | B12: 0.5 | C12: 2.5 | D12: 1.5 | F12: 0.5 | G12: 1
A13: Chocolate | B13: 0.5 | C13: 0.5 | D13: 1 | F13: 1.5 | G13: 1
A14: Seasalt | B14: 2.5 | C14: 3 | D14: 3 | E14: 0.5 | F14: 2.5 | G14: 1.5
A15: Caramel | B15: 2.5 | C15: 3 | D15: 3 | E15: 0.5 | F15: 2.5 | G15: 1.5
A16: Nile | B16: 0.5 | C16: 2 | D16: 2 | F16: 1 | G16: 1
A17: Bamboo | B17: 2 | C17: 3 | D17: 2 | E17: 1 | F17: 2 | G17: 2

Sheet Y2027 NPI - HVS (Gene) - Resour
A1: Resource Availability for Y2027 NPI Support
A2: SI Name | B2: Resource | C2: Y2026 Loading (Apr’26 ~ Sep’26) | D2: Total Resource (Cut Off Apr wk3) | E2: Resource Occupied for Y2026 Ramp (Apr’26 ~ Sep’26) | F2: Resource Leftover for Y2027 Brand-New Station NPI Build (Apr’26 ~ Sep’26) | G2: # of Stations Type can support (Refer CPT Y2027 RFP) | H2: Station Name can support (Refer CPT Y2027 RFP) | I2: Justification on why resource can support | J2: Space Supportability (Y/N) | K2: Machining Capacity Supportability (Y/N) | L2: Assembly Capacity Supportability (Y/N) | M2: Quality Capacity Supportability (Y/N) | N2: Station Name CANNOT Support (Refer CPT Y2027 RFP) & Justification
A3: HVS | B3: PM | C3: {=SUM(E3:E10)/SUM(D3:D10)} -> 0.63953488 | D3: 8 | E3: 5 | F3: {=D3-E3} -> 3 | G3: 3x | H3: iPhone V7x Station ALS-P / Odin Audio Open Short All-in-onc / IMU Camera / Open Conveyor | I3: Refer to V6x ALSP station in similar complexity, NPI resourced required as below: PM- 1x ME - 4x EE - 1x Assembly：15/line Quality- 1x For Odin support HVS has new resource hiring plan if required Production space is ok2support for China for China / India for India and Korea for any case if other site needs back-up | J3: Y | K3: Y | L3: Y | M3: Y | N3: iPhone V7x Station DCR / IQA AA Watch Conveyor Fact/Vent, Rotary
A4: HVS | B4: ME | D4: 25 | E4: 16 | F4: {=D4-E4} -> 9
A5: HVS | B5: EE | D5: 7 | E5: 4 | F5: {=D5-E5} -> 3
A6: HVS | B6: SW | D6: 12 | E6: 7 | F6: {=D6-E6} -> 5
A7: HVS | B7: FAE | D7: 56 | E7: 43 | F7: {=D7-E7} -> 13
A8: HVS | B8: Assembly | D8: 98 | E8: 50 | F8: {=D8-E8} -> 48
A9: HVS | B9: Debug | D9: 32 | E9: 24 | F9: {=D9-E9} -> 8
A10: HVS | B10: Quality | D10: 20 | E10: 16 | F10: {=D10-E10} -> 4

Sheet Y2027 NPI - HVS (Gene) - Y2026 
A1: Y2026 Loading Breakdown (Apr ~ Sep)
A2: SI Name | B2: Items | C2: Portable | D2: Pad | E2: Desktop | F2: Audio | G2: Watch | H2: Phone
A3: HVS | B3: Program | H3: V68
A4: HVS | B4: Station Name | H4: Scarlet Camera/Prox Scarlet IMU ALSP Helios
A5: HVS | B5: Station Total Demand | C5: {=SUM(C6:C13)} -> 0 | D5: {=SUM(D6:D13)} -> 0 | E5: {=SUM(E6:E13)} -> 0 | F5: {=SUM(F6:F13)} -> 0 | G5: {=SUM(G6:G13)} -> 0 | H5: {=SUM(H6:H13)} -> 165
A6: HVS | B6: PM | H6: 5
A7: HVS | B7: ME | H7: 16
A8: HVS | B8: EE | H8: 4
A9: HVS | B9: SW | H9: 7
A10: HVS | B10: FAE | H10: 43
A11: HVS | B11: Assembly | H11: 50
A12: HVS | B12: Debug | H12: 24
A13: HVS | B13: Quality | H13: 16

Sheet Y2027 NPI - HVS (Gene) - Y2027 
A1: Y2027 RFP Breakdown
A2: Collect data from the vendor and populate here
A3: HVS | B3: Items
B4: Program | C4: B798 | D4: V7x | E4: V7x
B5: Station Name | C5: Audio | D5: ALSP | E5: Odin
B6: Engagement Status (existing, new) | C6: New
B7: PM | C7: 2
B8: ME | C8: 6
B9: EE | C9: 2
B10: SW | C10: 4
B11: FAE | C11: 9
B12: Quality | C12: 3
B13: Assembly | C13: 36
B14: Debug | C14: 6

Sheet Y2027 NPI - HVS (Gene) - Drawin

Sheet Y2027 NPI - Pantamaster (JS) - 
A1: Resource Availability for Y2027 NPI Support
A2: SI Name | B2: Resource | C2: Y2026 Loading (Apr’26 ~ Sep’26) | D2: Total Resource (Cut Off Apr wk3) | E2: Resource Occupied for Y2026 Ramp (Apr’26 ~ Sep’26) | F2: Resource Leftover for Y2027 Brand-New Station NPI Build (Apr’26 ~ Sep’26) | G2: # of Stations Type can support (Refer CPT Y2027 RFP) | H2: Station Name can support (Refer CPT Y2027 RFP) | I2: Justification on why resource can support | J2: Space Supportability (Y/N) | K2: Machining Capacity Supportability (Y/N) | L2: Assembly Capacity Supportability (Y/N) | M2: Quality Capacity Supportability (Y/N) | N2: Station Name CANNOT Support (Refer CPT Y2027 RFP) & Justification
A3: Pentamaster | B3: PM | C3: {=SUM(E3:E10)/SUM(D3:D10)} -> 0.5390625 | D3: 15 | E3: 9 | F3: {=D3-E3} -> 6 | G3: 1x | H3: iPhone V7x Station SA-Barbie | I3: Refer to V7x SA Barbie station in similar complexity, NPI resourced required as below: PM - 1x ME - 1x EE - 1x SW - 1x FAE - 1x (China) Assembly - 2x Debug - 1x Quality - 1x | J3: Y | K3: Y | L3: Y | M3: Y | N3: -
A4: Pentamaster | B4: ME | D4: 20 | E4: 6 | F4: {=D4-E4} -> 14
A5: Pentamaster | B5: EE | D5: 8 | E5: 4 | F5: {=D5-E5} -> 4
A6: Pentamaster | B6: SW | D6: 20 | E6: 8 | F6: {=D6-E6} -> 12
A7: Pentamaster | B7: FAE | D7: 20 | E7: 16 | F7: {=D7-E7} -> 4
A8: Pentamaster | B8: Assembly | D8: 25 | E8: 15 | F8: {=D8-E8} -> 10
A9: Pentamaster | B9: Debug | D9: 12 | E9: 7 | F9: {=D9-E9} -> 5
A10: Pentamaster | B10: Quality | D10: 8 | E10: 4 | F10: {=D10-E10} -> 4

Sheet Y2027 NPI - Pantamaster (JS) -1
A1: Y2026 Loading Breakdown (Apr ~ Sep)
A2: SI Name | B2: Items | C2: Portable | D2: Pad | E2: Audio | F2: Watch | G2: Phone
A3: Pentamaster | B3: Program | C3: J62x | G3: V6x
A4: Pentamaster | B4: Station Name | C4: Chamber Conveyor | G4: BEXT XDXT FISH
A5: Pentamaster | B5: Station Total Demand | C5: 0 | G5: 5
A6: Pentamaster | B6: PM | C6: - | G6: 9
A7: Pentamaster | B7: ME | C7: - | G7: 4
A8: Pentamaster | B8: EE | C8: - | G8: 3
A9: Pentamaster | B9: SW | C9: - | G9: 8
A10: Pentamaster | B10: FAE | C10: 1 | G10: 15
A11: Pentamaster | B11: Assembly | C11: - | G11: 15
A12: Pentamaster | B12: Debug | C12: - | G12: 7
A13: Pentamaster | B13: Quality | C13: - | G13: 4

Sheet Y2027 NPI - CYG (Rick) - Resour
A1: Resource Availability for Y2027 NPI Support
A2: SI Name | B2: Resource | C2: Y2026 Loading (Apr’26 ~ Sep’26) | D2: Total Resource (Cut Off Apr wk3) | E2: Resource Occupied for Y2026 Ramp (Apr’26 ~ Sep’26) | F2: Resource Leftover for Y2027 Brand-New Station NPI Build (Apr’26 ~ Sep’26) | G2: # of Stations Type can support (Refer CPT Y2027 RFP) | H2: Station Name can support (Refer CPT Y2027 RFP) | I2: Justification on why resource can support | J2: Space Supportability (Y/N) | K2: Machining Capacity Supportability (Y/N) | L2: Assembly Capacity Supportability (Y/N) | M2: Quality Capacity Supportability (Y/N) | N2: Station Name CANNOT Support (Refer CPT Y2027 RFP) & Justification
B3: PM | C3: {=SUM(E3:E10)/SUM(D3:D10)} -> 0.4842615 | D3: 37 | E3: {=ROUNDUP('Y2027 NPI - CYG (Rick) - Y2026 '!C6+'Y2027 NPI - CYG (Rick) - Y2026 '!D6+'Y2027 NPI - CYG (Rick) - Y2026 '!E6+'Y2027 NPI - CYG (Rick) - Y2026 '!F6+'Y2027 NPI - CYG (Rick) - Y2026 '!G6+'Y2027 NPI - CYG (Rick) - Y2026 '!H6+'Y2027 NPI - CYG (Rick) - Y2026 '!I6,0)} -> 11 | F3: {=D3-E3} -> 26 | G3: 30x | H3: 1: Portable K12p DFU/FCT/SOC; 2: Portable K104 DFU/FCT/SOC; 3: Portable J702 DFU/SOC; 4: Pad J8x7 SOC; 5: Audio J727 DFU/FCT; 6: Phone V7x SA Carrier&Socket&Pogo&Tray&Holder&DCR； 7: Pencil B632&B582 FCT&Farosh FCT/BMU FCT/SA QT/Farosh/Zonai； 8:Watch N25x Combo CCD/ HSG-SA-Rioch/Burnin Rack/Sulu/FCT/DFU/BI； | I3: 1: Portable K12p DFU/FCT/SOC: Refer to K11p DFU/FCT/SOC station in similar complexity, NPI resourced required as below: ME - 2x, EE - 6x, SW - 1x, FAE - 6x; 2: Portable K104 DFU/FCT/SOC: Refer to J804 DFU/FCT/SOC station in similar complexity, NPI resourced required as below: ME - 1x, EE - 2x, SW - 1x, FAE - 2x; 3: Portable J702 DFU/SOC: Refer to J701 DFU/SOC station in similar complexity, NPI resourced required as below: ME - 1x, EE - 1x, FAE -1x; 4: Pad J8x7 SOC: Refer to Pad J7x7 MFCT station in similar complexity, NPI resourced required as below: ME - 1x, EE - 1x, FAE - 1x; 5: Audio J727 DFU/FCT: Refer to J747 DFU/FCT station in similar complexity, NPI resourced required as below: ME - 2x, EE - 2x, SW - 1x, FAE 2x; 6: Phone V7x SA Carrier&Socket&Pogo&Tray&Holder&DCR: Refer to V6x SA Carrier&Socket&Pogo&Tray&Holder&DCR station in similar complexity, NPI resourced required as below: ME - 3x, EE - 3x, SW - 1x, FAE 2x; 7: Pencil B632&B582 FCT&Farosh FCT/BMU FCT/SA QT/Farosh/Zonai: Refer to XB532&B482 FCT&Farosh FCT/BMU FCT/SA QT/Farosh/Zonai station in similar complexity, NPI resourced required as below: ME - 3x, EE - 4x, SW - 2x, FAE 4x; 8:Watch N25x Combo CCD/ HSG-SA-Rioch/Burnin Rack/Sulu/FCT/DFU/BI: Refer to N24x Combo CCD/ HSG-SA-Rioch/Burnin Rack/Sulu/FCT/DFU/BI station in similar complexity, NPI resourced required as below: ME - 4x, EE - 4x, SW - 1x, FAE 4x; | J3: Y | K3: Y | L3: Y | M3: Y | N3: N/A
B4: ME | D4: 42 | E4: {=ROUNDUP('Y2027 NPI - CYG (Rick) - Y2026 '!C7+'Y2027 NPI - CYG (Rick) - Y2026 '!D7+'Y2027 NPI - CYG (Rick) - Y2026 '!E7+'Y2027 NPI - CYG (Rick) - Y2026 '!F7+'Y2027 NPI - CYG (Rick) - Y2026 '!G7+'Y2027 NPI - CYG (Rick) - Y2026 '!H7+'Y2027 NPI - CYG (Rick) - Y2026 '!I7,0)} -> 11 | F4: {=D4-E4} -> 31
B5: EE | D5: 43 | E5: {=ROUNDUP('Y2027 NPI - CYG (Rick) - Y2026 '!C8+'Y2027 NPI - CYG (Rick) - Y2026 '!D8+'Y2027 NPI - CYG (Rick) - Y2026 '!E8+'Y2027 NPI - CYG (Rick) - Y2026 '!F8+'Y2027 NPI - CYG (Rick) - Y2026 '!G8+'Y2027 NPI - CYG (Rick) - Y2026 '!H8+'Y2027 NPI - CYG (Rick) - Y2026 '!I8,0)} -> 9 | F5: {=D5-E5} -> 34
B6: SW | D6: 22 | E6: {=ROUNDUP('Y2027 NPI - CYG (Rick) - Y2026 '!C9+'Y2027 NPI - CYG (Rick) - Y2026 '!D9+'Y2027 NPI - CYG (Rick) - Y2026 '!E9+'Y2027 NPI - CYG (Rick) - Y2026 '!F9+'Y2027 NPI - CYG (Rick) - Y2026 '!G9+'Y2027 NPI - CYG (Rick) - Y2026 '!H9+'Y2027 NPI - CYG (Rick) - Y2026 '!I9,0)} -> 5 | F6: {=D6-E6} -> 17
B7: FAE | D7: 48 | E7: {=ROUNDUP('Y2027 NPI - CYG (Rick) - Y2026 '!C10+'Y2027 NPI - CYG (Rick) - Y2026 '!D10+'Y2027 NPI - CYG (Rick) - Y2026 '!E10+'Y2027 NPI - CYG (Rick) - Y2026 '!F10+'Y2027 NPI - CYG (Rick) - Y2026 '!G10+'Y2027 NPI - CYG (Rick) - Y2026 '!H10+'Y2027 NPI - CYG (Rick) - Y2026 '!I10,0)} -> 15 | F7: {=D7-E7} -> 33
B8: Assembly | D8: 135 | E8: {=ROUNDUP('Y2027 NPI - CYG (Rick) - Y2026 '!C11+'Y2027 NPI - CYG (Rick) - Y2026 '!D11+'Y2027 NPI - CYG (Rick) - Y2026 '!E11+'Y2027 NPI - CYG (Rick) - Y2026 '!F11+'Y2027 NPI - CYG (Rick) - Y2026 '!G11+'Y2027 NPI - CYG (Rick) - Y2026 '!H11+'Y2027 NPI - CYG (Rick) - Y2026 '!I11,0)} -> 96 | F8: {=D8-E8} -> 39
B9: Debug | D9: 64 | E9: {=ROUNDUP('Y2027 NPI - CYG (Rick) - Y2026 '!C12+'Y2027 NPI - CYG (Rick) - Y2026 '!D12+'Y2027 NPI - CYG (Rick) - Y2026 '!E12+'Y2027 NPI - CYG (Rick) - Y2026 '!F12+'Y2027 NPI - CYG (Rick) - Y2026 '!G12+'Y2027 NPI - CYG (Rick) - Y2026 '!H12+'Y2027 NPI - CYG (Rick) - Y2026 '!I12,0)} -> 39 | F9: {=D9-E9} -> 25
B10: Quality | D10: 22 | E10: {=ROUNDUP('Y2027 NPI - CYG (Rick) - Y2026 '!C13+'Y2027 NPI - CYG (Rick) - Y2026 '!D13+'Y2027 NPI - CYG (Rick) - Y2026 '!E13+'Y2027 NPI - CYG (Rick) - Y2026 '!F13+'Y2027 NPI - CYG (Rick) - Y2026 '!G13+'Y2027 NPI - CYG (Rick) - Y2026 '!H13+'Y2027 NPI - CYG (Rick) - Y2026 '!I13,0)} -> 14 | F10: {=D10-E10} -> 8

Sheet Y2027 NPI - CYG (Rick) - Y2027 
A1: Y2027 RFP Breakdown
A2: SI Name | B2: Items | C2: Portable | D2: Pad | E2: Audio | F2: Watch | G2: Phone | H2: Pencil | I2: Apple TV | J2: SUM
B3: Program | C3: K12p/K104/J702 | D3: J8x7 | E3: J727 | F3: N25x | G3: V7x | H3: B632&B582 | I3: NA(Next Generation Pending Confirm)
B4: Station Name | C4: DFU/FCT/SOC | D4: SOC | E4: DFU/FCT | F4: Combo CCD/ HSG-SA-Rioch/Burnin Rack/Sulu/FCT/DFU/BI | G4: SACarrier&Socket&Pogo&Tray&Holder&DCR | H4: FCT&Farosh FCT/BMU FCT/SA QT/Farosh/Zonai | I4: NA
B5: Engagement Status (existing, new) | C5: Existing | D5: Existing | E5: Existing | F5: Existing | G5: Existing | H5: Existing | I5: NA
B6: PM | C6: 3 | D6: 1 | E6: 1 | F6: 3 | G6: 2 | H6: 3 | J6: {=SUM(C6:I6)} -> 13
B7: ME | C7: 4 | D7: 1 | E7: 2 | F7: 4 | G7: 3 | H7: 3 | J7: {=SUM(C7:I7)} -> 17
B8: EE | C8: 9 | D8: 1 | E8: 2 | F8: 4 | G8: 3 | H8: 4 | J8: {=SUM(C8:I8)} -> 23
B9: SW | C9: 2 | D9: 1 | E9: 1 | F9: 1 | G9: 1 | H9: 2 | J9: {=SUM(C9:I9)} -> 8
B10: FAE | C10: 9 | D10: 1 | E10: 2 | F10: 4 | G10: 2 | H10: 4 | J10: {=SUM(C10:I10)} -> 22
B11: Assembly | C11: 8 | D11: 1 | E11: 1.5 | F11: 6 | G11: 5 | H11: 2.5 | J11: {=SUM(C11:I11)} -> 24
B12: Debug | C12: 4 | D12: 0.5 | E12: 1 | F12: 4 | G12: 3 | H12: 2 | J12: {=SUM(C12:I12)} -> 14.5
B13: Quality | C13: 1 | D13: 0.2 | E13: 0.5 | F13: 1.5 | G13: 1.5 | H13: 0.5 | J13: {=SUM(C13:I13)} -> 5.2

Sheet Y2027 NPI - CYG (Rick) - Y2026 
A1: Y2026 MP Loading Breakdown (Apr ~ Sep)
A2: SI Name | B2: Items | C2: Portable | D2: Pad | E2: Audio | F2: Watch | G2: Phone | H2: Pencil | I2: Apple TV
B3: Program | C3: K11p/J804 | D3: J707/J737 (Already Finish MP Ramp by Y25 Q4) | E3: J747( Already finish MP Ramp by Y25 Q4) | F3: N23xN240 | G3: V6xV68 | H3: X3908 | I3: J529
B4: Station Name | C4: DFU/FCT/SOC | D4: MFCT | E4: DFU/FCT | F4: PFCT/PDFU/GK/Burnin/Combo CCD/Rioch/SA STHB/Sulu | G4: DFU/FCT/Carrier&Socket&Pogo&Tray&Holder&DCR Fixture | H4: SA QT/Aquila/Tip Power | I4: FCT/Button
B5: Station Total Demand | C5: 199 | D5: 24 | E5: 100 | F5: 1480x(Burnin 1039x; Other Station: 441x) | G5: 1368x (BT DFU/FCT: 359x ; SA Carrier&socket 1009x) | H5: 35 | I5: 39
B6: PM | C6: 2 | D6: 0.1 | E6: 0.1 | F6: 3 | G6: 4 | H6: 0.5 | I6: 0.5
B7: ME | C7: 1 | D7: 0.1 | E7: 0.1 | F7: 2 | G7: 6 | H7: 0.5 | I7: 0.5
B8: EE | C8: 1 | D8: 0.1 | E8: 0.1 | F8: 2 | G8: 4 | H8: 0.5 | I8: 0.5
B9: SW | C9: 1 | D9: 0.1 | E9: 0.1 | F9: 1 | G9: 1 | H9: 0.5 | I9: 0.5
B10: FAE | C10: 2 | D10: 0.1 | E10: 0.1 | F10: 5 | G10: 5 | H10: 1 | I10: 1
B11: Assembly | C11: 12 | D11: 0 | E11: 0 | F11: 36 | G11: 32 | H11: 8 | I11: 8
B12: Debug | C12: 5 | D12: 0 | E12: 0 | F12: 15 | G12: 14 | H12: 3 | I12: 2
B13: Quality | C13: 2 | D13: 0 | E13: 0 | F13: 6 | G13: 5 | H13: 0.5 | I13: 0.5

Sheet Y2027 NPI - Nextas (Jessie) - R
A1: Resource Availability for Y2027 NPI Support
A2: SI Name | B2: Resource | C2: Y2026 Loading (Apr’26 ~ Sep’26) | D2: Total Resource (Cut Off Apr wk3) | E2: Resource Occupied for Y2026 Ramp (Apr’26 ~ Sep’26) | F2: Resource Leftover for Y2027 Brand-New Station NPI Build (Apr’26 ~ Sep’26) | G2: # of Stations Type can support (Refer CPT Y2027 RFP) | H2: Station Name can support (Refer CPT Y2027 RFP) | I2: Justification on why resource can support | J2: Space Supportability (Y/N) | K2: Machining Capacity Supportability (Y/N) | L2: Assembly Capacity Supportability (Y/N) | M2: Quality Capacity Supportability (Y/N) | N2: Station Name CANNOT Support (Refer CPT Y2027 RFP) & Justification | O2: Bojay total resource
A3: Nextas | B3: PM | C3: {=SUM(E3:E10)/SUM(D3:D10)} -> 0.15728155 | D3: 59 | E3: 4 | F3: {=D3-E3} -> 55 | G3: 2x | H3: IQC AA stations DCR/OS Tests | I3: Refer to V64(RCAM IQC &RIM，FCAM-IQC&PAM，MLB modules in similar complexity, NPI resourced required as below: PM:4x ME - 4x EE - 3x FAE-5x Assembly:4 Quality: 3 | J3: Y | K3: Y | L3: Y | M3: Y | N3: No issue | O3: 98
A4: Nextas | B4: ME | D4: 52 | E4: 4 | F4: {=D4-E4} -> 48 | O4: 417
A5: Nextas | B5: EE | D5: 31 | E5: 3 | F5: {=D5-E5} -> 28 | O5: 210
A6: Nextas | B6: SW | D6: 53 | E6: 3 | F6: {=D6-E6} -> 50 | O6: 72
A7: Nextas | B7: FAE | D7: 95 | E7: 21 | F7: {=D7-E7} -> 74 | O7: 290
A8: Nextas | B8: Assembly | D8: 152 | E8: 22 | F8: {=D8-E8} -> 130 | O8: 266
A9: Nextas | B9: Debug | D9: 48 | E9: 21 | F9: {=D9-E9} -> 27 | O9: 103
A10: Nextas | B10: Quality | D10: 25 | E10: 3 | F10: {=D10-E10} -> 22 | O10: 87

Sheet Y2027 NPI - Nextas (Jessie) - Y
A1: Y2026 Loading Breakdown (Apr ~ Sep)
A2: SI Name | B2: Items | C2: Portable | D2: Pad | E2: Audio | F2: Watch | G2: Phone
A3: Nextas | B3: Program | G3: V7x
A4: Nextas | B4: Station Name | G4: IQC AA stations DCR/OS Tests
A5: Nextas | B5: Station Total Demand | G5: 2x
A6: Nextas | B6: PM | G6: 4
A7: Nextas | B7: ME | G7: 4
A8: Nextas | B8: EE | G8: 3
A9: Nextas | B9: SW | G9: 3
A10: Nextas | B10: FAE | G10: 21
A11: Nextas | B11: Assembly | G11: 22
A12: Nextas | B12: Debug | G12: 21
A13: Nextas | B13: Quality | G13: 3

Sheet Summary_Draft - 2027 NPI Suppor
B2: 2027 NPI Supportability Summary - APO
B3: 2027 SPOR - APO GSSM Recommendation | E3: Resource | H3: Capacity
B4: SI Name (APO GSM) | C4: 2027 RFP Stations (CPT GSSM RFPed Stations) | D4: APO GSSM Recommendations | E4: Y2026 Ramp Resource Loading & Issue Feedback (Apr’26 ~ Sep’26) | G4: Y2027 NPI Build Resource Supportability Assessment (Apr’26 ~ Sep’26) | H4: Space Supportability | I4: Machining Capacity Supportability | J4: Assembly Capacity Supportability | K4: Quality Capacity Supportability
B5: PRM (Anna) | C5: iPhone V7x Station SA Barbie ALS-P Watch FACT Cyan | D5: NOT Recommend to awarding any new business at 2027 given the resource capability limit and expertise mismatch. | E5: 0.68 | F5: Constraint technical resource: fully occupied by 2026 ramp with shortage escalation from CM(LXSZ/LXKU) Lack of solid internal operation management process: escalation from SQE/CapEx PM/Ops TE/HWTE on quality / delivery / OSS / on-site activities Lack of dedicated PM head to handle internal / external activities, led to Apple x-team spending huge efforts to bring up PRM cross areas | G5: ◉ High Risk Assessment: Resource qty sufficient Resource expertise NOT match new business requirement (Current - Board Test vs Needed - Display Conveyor) Resource working experience: 80% less than 1y on Apple biz | H5: ◉ Low Risk | I5: ◉ Low Risk | J5: ◉ Low Risk | K5: ◉ Low Risk
B6: Cencorp (Rick) | C6: iPhone V7x Station SA Barbie ALS-P Odim Watch N25x FACT Cyan iPad J807/J830 DVI Portable K12P/K104 SeaSalt Volga | D6: OK2Support | E6: 0.51 | F6: - No major highlight so far from X-team on Cencorp for Y26 Ramp - GSSM had deep dive review with Cencorp on resources including engineering, PM, FAE, production, OSS, and with name list supporting. Identified as medium-low risk. | G6: ◉ Medium Risk - Resource qty sufficient — after allocated to Y26 Ramp & Y27 NPI, there are still 11% resources leftover - Resource working experience: ~30% with +3 years experience with Cencorp - Cencorp has rich experiences on conveyor station from both iPhone V5x/V6x and Portable SeaSalt / Chocolate / Caramel | H6: ◉ Low Risk | I6: ◉ Low Risk | J6: ◉ Low Risk | K6: ◉ Low Risk
B7: CYG (Rick) | C7: iPhone V7x Station IQC AA Test DCR/OR Test | D7: OK2Support | E7: 0.48 | F7: - CYG FY26 demand 19% decreased compared to FY25 - CYG key talents remain high retention - No major highlight so far from X-team on CYG for Y26 ramp | G7: ◉ Low Risk - Standalone & less complex station - Only two new stations RFP engaged - Resource qty sufficient | H7: ◉ Low Risk | I7: ◉ Low Risk | J7: ◉ Low Risk | K7: ◉ Low Risk
B8: JLK (Sean) | C8: iPhone V7x Station SA Barbie ALS-P Conveyor Odin Conveyor iPad J8x7 station DVI Conveyor Audio B798 Station Touch Conveyor Force Conveyor FACT Conveyor | D8: Since no entirely new station has been deployed for JLK, the technical design has no major change from the previous project. Consequently, JLK is able to provide stable support to those stations. | E8: 0.59 | F8: No significant concerns have been identified regarding technical or operational resource quantities. However, quality-related issues remain, specifically: - Communication and data reporting competencies require further development. - Operations management headcount is sufficient, but the team lacks qualified project managers | G8: ◉ Low Risk | H8: ◉ Low Risk | I8: ◉ Low Risk | J8: ◉ Low Risk | K8: ◉ Low Risk
B9: Innorev (Fiona) | C9: iPhone V7x Station ALS-P Conveyor, Odin Conveyor, DCR/OS Tests, IQC AA stations. iPad J8x7 Station DVI Conveyor Watch N25x Station FACT21&Vent2 Conveyor, Conveyor Cyan Rotary Audio B798 station All in One Case, Open Short, IMU Camera. | D9: OK to support the CPT team’s RFP’ed stations except Odin Conveyer. Odin Conveyer is brand new to Innorev. | E9: 0.51 | F9: No major resource qtys issue for operation team but encountered DRI capability issue: An experienced operation mgr is expected on board asap; Sense & accuracy of communications is weak; OSS management team’s capability is below expectation. Engineer & operation team needs be more collaborated to ensure smooth transition from NPI to ramp; Quality team’s capability issue is a big issue which are continuously hi-lighted by SQE. | G9: ◉ High Risk Assessment Quality team qtys are sufficient but the capability of DRIs need to continuously improve. | H9: ◉ Low Risk | I9: ◉ Low Risk | J9: ◉ Low Risk | K9: ◉ Low Risk
B10: HVS (Gene) | C10: iPhone V7x Station ALS-P Conveyor, Odin Conveyor, DCR/OS Tests, IQC AA stations. Watch N25x Station FACT21&Vent2 Conveyor, Conveyor Cyan Rotary Audio B798 station All in One Case, Open Short, IMU Camera. | D10: OK to support stations limited to [1] Audio - 3 stations [2] Phone V7x - ALSP Same message from SI also shared with CPT team | E10: 0.64 | F10: X-team overall feedback from FXGL show HVS need to improve overall communication, PM capability, language barriers and OSS capability Very tough to own communication with Primary vendor to follow on-going design change / documents and parts purchasing - directly impacting EQ readiness HVS China plant capability should be improved further to support China local demand especially quality and purchases 2026 TE 4 stations will be under offline test and validation run in parallel and with on-going feedback/design change current resources are expected to stay longer than expected for now | G10: ◉ High Risk Assessment: R&D / PM resource is OK2support limited stations and also need to focus on improving capability in China plan PM need to increase resource with language capability and also need to hired from local to decrease the reliance from Korea HQ TE resource also need to be allocated to support other programs CPT started engaging for India TE No enough resource to work to bridge/sync to primary SI for on-going works Similar feedback was also shared by SI directly to CPT team | H10: ◉ Low Risk - Need to be revisited after post V68 (it can require separate space not with the program on the same floor)/ 27 AE demand | I10: ◉ Low Risk | J10: ◉ Low Risk | K10: ◉ Low Risk - assuming latest improvement from SQE audit can stay with on-going improvement
B11: Pantamaster (JS) | C11: iPhone V7x Station SA Barbie | D11: OK2Support | E11: {='Y2027 NPI - Pantamaster (JS) - '!C3} -> 0.5390625 | F11: ◉ Low Risk - No resource issue to support TE. - Current TE resources have Apple project experience exposure. | G11: ◉ Low Risk | H11: ◉ Low Risk | I11: ◉ Low Risk | J11: ◉ Low Risk | K11: ◉ Low Risk
B12: Nextas (Jessie) | C12: iPhone V7x Station IQC AA stations DCR/OS Tests | D12: OK2Support | E12: D | F12: ◉ Low Risk -No resource issue as same group with Bojay which’s strong Engineer support NPI if need -Share same VN facility with Bojay, Lasteck will be ready to use by May/E | G12: ◉ Low Risk | H12: ◉ Low Risk | I12: ◉ Low Risk | J12: ◉ Low Risk | K12: ◉ Low Risk

Sheet Y2027 NPI - PRM (Anna) - 4_13v 
A1: Resource Availability for Y2027 NPI Support
A2: SI Name | B2: Resource | C2: Y2026 Loading (Apr’26 ~ Sep’26) | D2: Total Resource (Cut Off Apr wk3) | E2: Resource Occupied for Y2026 Ramp (Apr’26 ~ Sep’26) | F2: Resource Leftover for Y2027 Brand-New Station NPI Build (Apr’26 ~ Sep’26) | G2: # of Stations Type can support (Refer CPT Y2027 RFP) | H2: Station Name can support (Refer CPT Y2027 RFP) | I2: Justification on why resource can support | J2: Space Supportability (Y/N) | K2: Machining Capacity Supportability (Y/N) | L2: Assembly Capacity Supportability (Y/N) | M2: Quality Capacity Supportability (Y/N) | N2: Station Name CANNOT Support (Refer CPT Y2027 RFP) & Justification
A3: PRM | B3: PM | C3: {=SUM(E3:E11)/SUM(D3:D11)} -> 0.67700987 | D3: 69 | E3: {=SUM('Y2027 NPI - PRM (Anna) - 4_13v1'!C6:H6)} -> 40 | F3: {=D3-E3} -> 29 | G3: 4x | H3: iPhone V7x Station SA Barbie ALS-P Watch FACT Cyan | I3: Refer to V6x FACTVENT station in similar complexity, NPI resourced required as below: PM- 1x ME - 5x EE - 5x VE - 3x Assembly：18/line Quality- 2x | J3: Y | K3: Y | L3: Y | M3: Y
A4: PRM | B4: ME | D4: 123 | E4: {=SUM('Y2027 NPI - PRM (Anna) - 4_13v1'!C7:H7)} -> 61 | F4: {=D4-E4} -> 62
A5: PRM | B5: EE | D5: 75 | E5: {=SUM('Y2027 NPI - PRM (Anna) - 4_13v1'!C8:H8)} -> 62 | F5: {=D5-E5} -> 13
A6: PRM | B6: SW | D6: {=5+16+17+24} -> 62 | E6: {=SUM('Y2027 NPI - PRM (Anna) - 4_13v1'!C9:H9)} -> 43 | F6: {=D6-E6} -> 19
A7: PRM | B7: FAE | D7: {=55+36} -> 91 | E7: {=SUM('Y2027 NPI - PRM (Anna) - 4_13v1'!C10:H10)} -> 67 | F7: {=D7-E7} -> 24
A8: PRM | B8: Assembly | D8: {=40+88+48} -> 176 | E8: {=SUM('Y2027 NPI - PRM (Anna) - 4_13v1'!C11:H11)} -> 111 | F8: {=D8-E8} -> 65
A9: PRM | B9: Debug | D9: {=34+21} -> 55 | E9: {=SUM('Y2027 NPI - PRM (Anna) - 4_13v1'!C12:H12)} -> 52 | F9: {=D9-E9} -> 3
A10: PRM | B10: Quality | D10: {=13+32} -> 45 | E10: {=SUM('Y2027 NPI - PRM (Anna) - 4_13v1'!C13:H13)} -> 38 | F10: {=D10-E10} -> 7
A11: PRM | B11: VE | D11: 13 | E11: {=SUM('Y2027 NPI - PRM (Anna) - 4_13v1'!C14:H14)} -> 6 | F11: {=D11-E11} -> 7

Sheet Y2027 NPI - PRM (Anna) - 4_13v1
A1: Y2026 Loading Breakdown (Apr ~ Sep)
A2: SI Name | B2: Items | C2: Portable | D2: Pad | E2: Desktop | F2: Audio | G2: Watch | H2: Phone
A3: PRM | B3: Program | C3: J701/K104/J91a/K11p | D3: J8x7/J9xx/J510 | E3: J775/J873/J883/J83x | F3: B798/B868/B790/B747a/B727 | G3: N23x/N240 | H3: V68/V6X
A4: PRM | B4: Station Name | C4: Snoop/Snoop-c/RC FACT/FACT conveyor | D4: FCT/DFU/SOC | E4: FCT/DFU/SOC | F4: Flex FCT/Flex Mic/FCT | G4: Panel DFU/FCT/GK FCT/BI/Conveyor/Bamboo/Marge&X-talk | H4: Grape/Helios/FACT & VENT /Snoop C
A5: PRM | B5: Station Total Demand | C5: {=SUM(C6:C13)} -> 73 | D5: {=SUM(D6:D13)} -> 42 | E5: {=SUM(E6:E13)} -> 59 | F5: {=SUM(F6:F13)} -> 72 | G5: {=SUM(G6:G13)} -> 56 | H5: {=SUM(H6:H13)} -> 172
A6: PRM | B6: PM | C6: {=2+5} -> 7 | D6: 2 | E6: {=3+1} -> 4 | F6: {=7+2} -> 9 | G6: {=2+2+2} -> 6 | H6: {=8+4} -> 12
A7: PRM | B7: ME | C7: {=5+7} -> 12 | D7: 5 | E7: {=5+2} -> 7 | F7: {=5+3} -> 8 | G7: {=3+2+1} -> 6 | H7: {=10+13} -> 23
A8: PRM | B8: EE | C8: {=1+10} -> 11 | D8: 8 | E8: {=8+2} -> 10 | F8: {=8+1} -> 9 | G8: {=5+1+2} -> 8 | H8: {=6+10} -> 16
A9: PRM | B9: SW | C9: {=1+6+3} -> 10 | D9: 8 | E9: {=6+2} -> 8 | F9: {=10+1} -> 11 | G9: {=3+1} -> 4 | H9: 2
A10: PRM | B10: FAE | C10: {=4+4} -> 8 | D10: 8 | E10: {=8+1} -> 9 | F10: {=9+3} -> 12 | G10: {=3+1+4} -> 8 | H10: 22
A11: PRM | B11: Assembly | C11: 14 | D11: 5 | E11: 8 | F11: 12 | G11: 15 | H11: {=13+18+18+8} -> 57
A12: PRM | B12: Debug | C12: 6 | D12: 3 | E12: 7 | F12: 6 | G12: 5 | H12: {=6+6+13} -> 25
A13: PRM | B13: Quality | C13: 5 | D13: 3 | E13: 6 | F13: 5 | G13: 4 | H13: {=7+8} -> 15
A14: PRM | B14: VE | H14: 6

Sheet Y2027 NPI - Accurate (Pratiksha
B2: Resource Availability for Y2027 NPI Support
B3: SI Name | C3: Resource | D3: Y2026 Loading | E3: Total Resource | F3: Resource Occupied for Y2026 Ramp | G3: Resource Leftover for Y2027 Brand-New Station NPI Build | H3: # of Stations Type can support | I3: Space Supportability (Y/N) | J3: Machining Capacity Supportability (Y/N) | K3: Assembly Capacity Supportability (Y/N) | L3: Quality Capacity Supportability (Y/N)
B4: PRM | C4: PM | D4: {=SUM(F4:F11)/SUM(E4:E11)} -> 0.6 | E4: {=SUM(F4:G4)} -> 6 | F4: 3 | G4: 3 | H4: 4x | I4: Y | J4: Y | K4: Y | L4: Y
B5: PRM | C5: ME | E5: {=SUM(F5:G5)} -> 10 | F5: 4 | G5: 6
B6: PRM | C6: EE | E6: {=SUM(F6:G6)} -> 10 | F6: 4 | G6: 6
B7: PRM | C7: SW | E7: {=SUM(F7:G7)} -> 6 | F7: 2 | G7: 4
B8: PRM | C8: FAE | E8: {=SUM(F8:G8)} -> 0 | F8: 0 | G8: 0
B9: PRM | C9: Assembly | E9: {=SUM(F9:G9)} -> 35 | F9: 25 | G9: 10
B10: PRM | C10: Debug | E10: {=SUM(F10:G10)} -> 2 | F10: 2 | G10: 0
B11: PRM | C11: Quality | E11: {=SUM(F11:G11)} -> 6 | F11: 5 | G11: 1

Sheet Y2027 NPI - SFO (Ankan) - 5_18 
B2: Resource Availability for Y2027 NPI Support
B3: SI Name | C3: Resource | D3: Y2026 Loading | E3: Total Resource | F3: Resource Occupied for Y2026 Ramp | G3: Resource Leftover for Y2027 Brand-New Station NPI Build | H3: # of Stations Type can support | I3: Space Supportability (Y/N) | J3: Machining Capacity Supportability (Y/N) | K3: Assembly Capacity Supportability (Y/N) | L3: Quality Capacity Supportability (Y/N)
B4: PRM | C4: PM | D4: {=SUM(F4:F11)/SUM(E4:E11)} -> 0.38927739 | E4: {=SUM(F4:G4)} -> 16 | F4: 6 | G4: 10 | H4: 30 | I4: Yes | J4: Yes | K4: Yes | L4: Yes
B5: PRM | C5: ME | E5: {=SUM(F5:G5)} -> 62 | F5: 31 | G5: 31
B6: PRM | C6: EE | E6: {=SUM(F6:G6)} -> 49 | F6: 13 | G6: 36
B7: PRM | C7: SW | E7: {=SUM(F7:G7)} -> 35 | F7: 6 | G7: 29
B8: PRM | C8: FAE | E8: {=SUM(F8:G8)} -> 8 | F8: 3 | G8: 5
B9: PRM | C9: Assembly | E9: {=SUM(F9:G9)} -> 170 | F9: 74 | G9: 96
B10: PRM | C10: Debug | E10: {=SUM(F10:G10)} -> 5 | F10: 2 | G10: 3
B11: PRM | C11: Quality | E11: {=SUM(F11:G11)} -> 84 | F11: 32 | G11: 52

Sheet _old_ 2027 NPI Supportability S
B2: 2027 SPOR - APO GSSM Recommendation | E2: Resource | H2: Capacity
B3: SI Name (APO GSM) | C3: 2027 RFP Stations (CPT GSSM RFPed Stations) | D3: APO GSSM Recommendations | E3: Y2026 Ramp Resource Loading & Issue Feedback (Apr’26 ~ Sep’26) | G3: Y2027 NPI Build Resource Supportability Assessment (Apr’26 ~ Sep’26) | H3: Space Supportability | I3: Machining Capacity Supportability | J3: Assembly Capacity Supportability | K3: Quality Capacity Supportability
B4: PRM (Anna) | C4: iPhone V7x Station SA Barbie ALS-P Watch FACT Cyan | D4: NOT Recommend to awarding any new business at 2027 given the resource constraint and unvalidated expertise | E4: 0.81 | F4: Constraint Resource: PM/Technical/OSS shortage escalation Lack of operation management system: escalation from SQE/CapEx PM/Tech Ops on quality / delivery / on-site activities Lack of dedicated PM head to handle internal / external activities, led to Apple x-team spending huge efforts to bring up PRM cross areas | G4: ◉ High Risk Assessment: Reported idle resource qty ONLY ok2support iPhone V7x ALSP Resource expertise NOT validated if able to meet new business requirement as all of them current scope at PRM are Non-A biz Help Needed: HWTE validate resource expertise upon request | H4: ◉ Low Risk | I4: ◉ Low Risk | J4: ◉ Low Risk | K4: ◉ Low Risk
B5: Cencorp (Rick) | C5: iPhone V7x Station SA Barbie ALS-P Odim Watch N25x FACT Cyan iPad J807/J830 DVI Portable K12P/K104 SeaSalt Volga | D5: OK2Support | E5: 0.51 | F5: - No major highlight so far from X-team on Cencorp for Y26 Ramp - GSSM had deep dive review with Cencorp on resources including engineering, PM, FAE, production, OSS, and with name list supporting. Identified as medium-low risk. | G5: ◉ Medium Risk Assessment - Cencorp has rich experiences on conveyor station from both iPhone (Jasmine, Clematis, BEXT) and Portable (SeaSalt / Chocolate / Caramel) - Resource qty sufficient — after allocated to Y26 Ramp & Y27 NPI, there are still 11% resources leftover, however they are heavily engaged on ramps across CN/VN for multiple non-phone programs - Resource working experience: ~30% with +3 years experience with Cencorp | H5: ◉ Low Risk | I5: ◉ Low Risk | J5: ◉ Low Risk | K5: ◉ Low Risk
B6: Innorev (Fiona) | C6: iPhone V7x Station ALS-P Conveyor, Odin Conveyor, DCR/OS Tests, IQC AA stations. iPad J8x7 Station DVI Conveyor Watch N25x Station FACT21&Vent2 Conveyor, Conveyor Cyan Rotary Audio B798 station All in One Case, Open Short, IMU Camera. | D6: OK2Support CPT RFP’ed stations except Odin Conveyer (brand new to Innorev) | E6: 0.51 | F6: No major resource qtys issue for operation team but encountered DRI capability issue: An experienced operation mgr is expected on board asap; Sense & accuracy of communications is weak; OSS management team’s capability is below expectation. Engineer & operation team needs be more collaborated to ensure smooth transition from NPI to ramp; Quality team’s capability issue is a big issue which are continuously hi-lighted by SQE. | G6: ◉ High Risk Assessment Quality team qtys are sufficient but the capability of DRIs need to continuously improve. | H6: ◉ Low Risk | I6: ◉ Low Risk | J6: ◉ Low Risk | K6: ◉ Low Risk
B7: HVS (Gene) | C7: iPhone V7x Station ALS-P Conveyor, Odin Conveyor, DCR/OS Tests, IQC AA stations. Watch N25x Station FACT21&Vent2 Conveyor, Conveyor Cyan Rotary Audio B798 station All in One Case, Open Short, IMU Camera. | D7: OK2Support ONLY below stations [1] Audio - 3 stations [2] Phone V7x - ALSP Same message from SI also shared with CPT team | E7: 0.64 | F7: X-team overall feedback from FXGL show HVS need to improve overall communication, PM capability, language barriers and OSS capability Very tough to own communication with Primary vendor to follow on-going design change / documents and parts purchasing - directly impacting EQ readiness HVS China plant capability should be improved further to support China local demand especially quality and purchases 2026 TE 4 stations will be under offline test and validation run in parallel and with on-going feedback/design change current resources are expected to stay longer than expected for now | G7: ◉ High Risk Assessment: R&D / PM resource is OK2support limited stations and also need to focus on improving capability in China plan PM need to increase resource with language capability and also need to hired from local to decrease the reliance from Korea HQ TE resource also need to be allocated to support other programs CPT started engaging for India TE No enough resource to work to bridge/sync to primary SI for on-going works Similar feedback was also shared by SI directly to CPT team | H7: ◉ Low Risk | I7: ◉ Low Risk | J7: ◉ Low Risk | K7: ◉ Low Risk
B8: JLK (Sean) | C8: iPhone V7x Station SA Barbie ALS-P Conveyor Odin Conveyor iPad J8x7 station DVI Conveyor Audio B798 Station Touch Conveyor Force Conveyor FACT Conveyor | D8: OK2Support | E8: 0.59 | F8: - No significant concerns have been identified regarding technical or operational resource quantities. However, quality-related issues remain, specifically: - Communication and data reporting competencies require further development. - Operations management headcount is sufficient, but the team lacks qualified project managers | G8: ◉ Low Risk Since no entirely new station has been deployed for JLK, the technical design has no major change from the previous project. Consequently, JLK is able to provide stable support to those stations. | H8: ◉ Low Risk | I8: ◉ Low Risk | J8: ◉ Low Risk | K8: ◉ Low Risk
B9: Pantamaster (JS) | C9: iPhone V7x Station SA Barbie | D9: OK2Support | E9: {='Y2027 NPI - Pantamaster (JS) - '!C3} -> 0.5390625 | F9: - No resource issue to support TE. - Current TE resources have Apple project experience exposure. | G9: ◉ Low Risk | H9: ◉ Low Risk | I9: ◉ Low Risk | J9: ◉ Low Risk | K9: ◉ Low Risk
B10: CYG (Rick) | C10: iPhone V7x Station IQC AA Test DCR/OR Test | D10: OK2Support | E10: 0.48 | F10: - CYG FY26 demand 19% decreased compared to FY25 - CYG key talents remain high retention - No major highlight so far from X-team on CYG for Y26 ramp | G10: ◉ Low Risk - Standalone & less complex station - Only two new stations RFP engaged - Resource qty sufficient | H10: ◉ Low Risk | I10: ◉ Low Risk | J10: ◉ Low Risk | K10: ◉ Low Risk
B11: Nextas (Jessie) | C11: iPhone V7x Station IQC AA stations DCR/OS Tests | D11: OK2Support | E11: 0.16 | F11: -No resource issue as same group with Bojay which’s strong Engineer support NPI if need -Share same VN facility with Bojay, Lasteck will be ready to use by May/E | G11: ◉ Low Risk | H11: ◉ Low Risk | I11: ◉ Low Risk | J11: ◉ Low Risk | K11: ◉ Low Risk

Sheet Sheet 1 - Commercial Levers
A1: Commercial Levers
A2: Vendor | B2: VN/CN cost parity | C2: Lot 0 items/cal kit reduction | D2: Labor/processing rates | E2: Retrofit | F2: Flat 10% reduction | G2: Common Module benchmark
A3: Cencorp | B3: Y
A4: JLK | B4: Y
A5: Innorev | B5: Y
A6: HVS
A7: VVDN
A8: PRM
A9: Penta
A10: Amp
A11: CYG
A12: Nextas
A13: Details | B13: Communicated as expectation; timeline pull in | C13: 5%-10% cost reduction | D13: Meet targets from last year as NTE | E13: All conveyors 5% retrofit cost of NB (except gsm exceptions)
